[
  {
    "category": "verified_unlabeled",
    "file_name": "log_0064_flyaway.bin",
    "source_path": "downloads/log_0064_flyaway.bin",
    "source_relative_path": "downloads/log_0064_flyaway.bin",
    "size_bytes": 1011712,
    "sha256": "01803ce998a260eb56293a2e805ce3350a9b3d1fe00fb0a90bedc149849e611e",
    "duplicate_count": 1,
    "duplicate_sources": [
      "downloads/log_0064_flyaway.bin"
    ],
    "raw_label": "FLYAWAY",
    "mapped_label": "",
    "trainable": false,
    "source_type": "ArduPilot_Discuss",
    "source_url": "https://discuss.ardupilot.org/t/rtl-flyaway-bad-pos-among-others/53951",
    "resolved_download_url": "https://discuss.ardupilot.org/uploads/short-url/yfNjMtfjpugV5ctr1CvSftmRlEF.BIN",
    "provenance_status": "downloaded",
    "provenance_records": [
      {
        "manifest": "crawler_manifest.csv",
        "status": "downloaded",
        "label_raw": "FLYAWAY",
        "source_type": "ArduPilot_Discuss",
        "thread_url": "https://discuss.ardupilot.org/t/rtl-flyaway-bad-pos-among-others/53951",
        "resolved_url": "https://discuss.ardupilot.org/uploads/short-url/yfNjMtfjpugV5ctr1CvSftmRlEF.BIN"
      },
      {
        "manifest": "crawler_manifest_v2.csv",
        "status": "downloaded",
        "label_raw": "FLYAWAY",
        "source_type": "ArduPilot_Discuss",
        "thread_url": "https://discuss.ardupilot.org/t/rtl-flyaway-bad-pos-among-others/53951",
        "resolved_url": "https://discuss.ardupilot.org/uploads/short-url/yfNjMtfjpugV5ctr1CvSftmRlEF.BIN"
      }
    ],
    "expert_username": "xfacta",
    "expert_quote": "Edit: Mike Boland beat me to it There\u2019s a large weight imbalance, heavy towards the rear. This is causing motors 1 and 3 to be doing almost nothing, while motors 2 and 4 work close to their maximum. This leaves no headroom for attitude control. Attitude wasnt great to begin with, but it gets worse as the flight goes on, the motor outputs go all over the place Z axis vibration looks a bit bad, and is usually the numbe",
    "parse_message_count": 3000,
    "parse_message_types": 44
  },
  {
    "category": "verified_unlabeled",
    "file_name": "log_0029_battery_failsafe.bin",
    "source_path": "downloads/log_0029_battery_failsafe.bin",
    "source_relative_path": "downloads/log_0029_battery_failsafe.bin",
    "size_bytes": 139194,
    "sha256": "0818fe7e5ce3cda47fdf3fef42cb2d02963f354b8b18750fa59edb3d0e035719",
    "duplicate_count": 1,
    "duplicate_sources": [
      "downloads/log_0029_battery_failsafe.bin"
    ],
    "raw_label": "BATTERY_FAILSAFE",
    "mapped_label": "",
    "trainable": false,
    "source_type": "ArduPilot_Discuss",
    "source_url": "https://discuss.ardupilot.org/t/pixhawk-clone-2-4-8-motors-not-running-in-the-same-speed/93719",
    "resolved_download_url": "https://discuss.ardupilot.org/uploads/short-url/7Dif4AJuMoDmXUhkloHl8MAlSW4.bin",
    "provenance_status": "downloaded",
    "provenance_records": [
      {
        "manifest": "crawler_manifest.csv",
        "status": "downloaded",
        "label_raw": "BATTERY_FAILSAFE",
        "source_type": "ArduPilot_Discuss",
        "thread_url": "https://discuss.ardupilot.org/t/pixhawk-clone-2-4-8-motors-not-running-in-the-same-speed/93719",
        "resolved_url": "https://discuss.ardupilot.org/uploads/short-url/7Dif4AJuMoDmXUhkloHl8MAlSW4.bin"
      },
      {
        "manifest": "crawler_manifest_v2.csv",
        "status": "downloaded",
        "label_raw": "BATTERY_FAILSAFE",
        "source_type": "ArduPilot_Discuss",
        "thread_url": "https://discuss.ardupilot.org/t/pixhawk-clone-2-4-8-motors-not-running-in-the-same-speed/93719",
        "resolved_url": "https://discuss.ardupilot.org/uploads/short-url/7Dif4AJuMoDmXUhkloHl8MAlSW4.bin"
      }
    ],
    "expert_username": "xfacta",
    "expert_quote": "First thing - upgrade to latest stable firmware before doing anything else, version 3.6.8 is very old now. Select the flight controller as Pixhawk1 Next thing - don\u2019t rush into jumping down my list to ESC calibration and and trying to arm and fly again - work through all these things in order. Put ARMING_CHECK back to 1 Also set BATT_FS_CRT_ACT,1 BATT_FS_LOW_ACT,2 MOT_PWM_MIN,1000 MOT_PWM_MAX,2000 Check your radio fa",
    "parse_message_count": 3000,
    "parse_message_types": 39
  },
  {
    "category": "verified_unlabeled",
    "file_name": "log_0033_hardware_failure.bin",
    "source_path": "downloads/log_0033_hardware_failure.bin",
    "source_relative_path": "downloads/log_0033_hardware_failure.bin",
    "size_bytes": 21426176,
    "sha256": "15deab36497ed66aba1b18194547f8b39e9b40d2cab58524a3654c4cee916521",
    "duplicate_count": 1,
    "duplicate_sources": [
      "downloads/log_0033_hardware_failure.bin"
    ],
    "raw_label": "HARDWARE_FAILURE",
    "mapped_label": "",
    "trainable": false,
    "source_type": "ArduPilot_Discuss",
    "source_url": "https://discuss.ardupilot.org/t/failure-to-launch/80437",
    "resolved_download_url": "https://www.dropbox.com/s/cykrncm13hgnhtq/2021-12-23-1.BIN?dl=1",
    "provenance_status": "downloaded",
    "provenance_records": [
      {
        "manifest": "crawler_manifest.csv",
        "status": "downloaded",
        "label_raw": "HARDWARE_FAILURE",
        "source_type": "ArduPilot_Discuss",
        "thread_url": "https://discuss.ardupilot.org/t/failure-to-launch/80437",
        "resolved_url": "https://www.dropbox.com/s/cykrncm13hgnhtq/2021-12-23-1.BIN?dl=1"
      },
      {
        "manifest": "crawler_manifest_v2.csv",
        "status": "downloaded",
        "label_raw": "HARDWARE_FAILURE",
        "source_type": "ArduPilot_Discuss",
        "thread_url": "https://discuss.ardupilot.org/t/failure-to-launch/80437",
        "resolved_url": "https://www.dropbox.com/s/cykrncm13hgnhtq/2021-12-23-1.BIN?dl=1"
      }
    ],
    "expert_username": "timtuxworth",
    "expert_quote": "I\u2019ve recently experienced some odd takeoff behaviour with my Bixinator. I have everything setup for auto launch in my Mission, I arm the plane and throw it and some random (apparently) percentage of the time the motor doesn\u2019t fire and it just glides to the ground. If I reset the mission and try again, it sometimes works. Or sometimes it works the first time. I haven\u2019t been able to figure out what I\u2019m doing wrong. Thi",
    "parse_message_count": 3000,
    "parse_message_types": 52
  },
  {
    "category": "verified_labeled",
    "file_name": "log_0041_mechanical_failure.bin",
    "source_path": "downloads/log_0041_mechanical_failure.bin",
    "source_relative_path": "downloads/log_0041_mechanical_failure.bin",
    "size_bytes": 958464,
    "sha256": "1796486e9ac43407765587df16a6d0fb6577cd7bee4c76b8c82ce0196075413a",
    "duplicate_count": 1,
    "duplicate_sources": [
      "downloads/log_0041_mechanical_failure.bin"
    ],
    "raw_label": "MECHANICAL_FAILURE",
    "mapped_label": "mechanical_failure",
    "trainable": true,
    "source_type": "ArduPilot_Discuss",
    "source_url": "https://discuss.ardupilot.org/t/3-6-7-installed-and-tested-drone-crashed-firmware-issue-or-battery-or-something-else-unable-to-find-out/39722",
    "resolved_download_url": "https://discuss.ardupilot.org/uploads/default/original/3X/4/2/42f32ae9f1ce3c0c09b8fb9102d210f581f4618d.bin",
    "provenance_status": "downloaded",
    "provenance_records": [
      {
        "manifest": "crawler_manifest.csv",
        "status": "downloaded",
        "label_raw": "MECHANICAL_FAILURE",
        "source_type": "ArduPilot_Discuss",
        "thread_url": "https://discuss.ardupilot.org/t/3-6-7-installed-and-tested-drone-crashed-firmware-issue-or-battery-or-something-else-unable-to-find-out/39722",
        "resolved_url": "https://discuss.ardupilot.org/uploads/default/original/3X/4/2/42f32ae9f1ce3c0c09b8fb9102d210f581f4618d.bin"
      },
      {
        "manifest": "crawler_manifest_v2.csv",
        "status": "downloaded",
        "label_raw": "MECHANICAL_FAILURE",
        "source_type": "ArduPilot_Discuss",
        "thread_url": "https://discuss.ardupilot.org/t/3-6-7-installed-and-tested-drone-crashed-firmware-issue-or-battery-or-something-else-unable-to-find-out/39722",
        "resolved_url": "https://discuss.ardupilot.org/uploads/default/original/3X/4/2/42f32ae9f1ce3c0c09b8fb9102d210f581f4618d.bin"
      }
    ],
    "expert_username": "",
    "expert_quote": "",
    "parse_message_count": 3000,
    "parse_message_types": 49
  },
  {
    "category": "verified_labeled",
    "file_name": "log_0039_mechanical_failure.bin",
    "source_path": "downloads/log_0039_mechanical_failure.bin",
    "source_relative_path": "downloads/log_0039_mechanical_failure.bin",
    "size_bytes": 1124580,
    "sha256": "1de0bcaf777b20c7f69c2948472c1ad5e87eb34dfe40c5bbce29d77f969acdf8",
    "duplicate_count": 1,
    "duplicate_sources": [
      "downloads/log_0039_mechanical_failure.bin"
    ],
    "raw_label": "MECHANICAL_FAILURE",
    "mapped_label": "mechanical_failure",
    "trainable": true,
    "source_type": "ArduPilot_Discuss",
    "source_url": "https://discuss.ardupilot.org/t/esc-failure-or-signal-lost-thank-s-for-help/18093",
    "resolved_download_url": "https://discuss.ardupilot.org/uploads/default/original/2X/0/03b63344fa64dee0ec39072ca06b47f34203c23b.BIN",
    "provenance_status": "downloaded",
    "provenance_records": [
      {
        "manifest": "crawler_manifest.csv",
        "status": "downloaded",
        "label_raw": "MECHANICAL_FAILURE",
        "source_type": "ArduPilot_Discuss",
        "thread_url": "https://discuss.ardupilot.org/t/esc-failure-or-signal-lost-thank-s-for-help/18093",
        "resolved_url": "https://discuss.ardupilot.org/uploads/default/original/2X/0/03b63344fa64dee0ec39072ca06b47f34203c23b.BIN"
      },
      {
        "manifest": "crawler_manifest_v2.csv",
        "status": "downloaded",
        "label_raw": "MECHANICAL_FAILURE",
        "source_type": "ArduPilot_Discuss",
        "thread_url": "https://discuss.ardupilot.org/t/esc-failure-or-signal-lost-thank-s-for-help/18093",
        "resolved_url": "https://discuss.ardupilot.org/uploads/default/original/2X/0/03b63344fa64dee0ec39072ca06b47f34203c23b.BIN"
      }
    ],
    "expert_username": "",
    "expert_quote": "",
    "parse_message_count": 3000,
    "parse_message_types": 40
  },
  {
    "category": "verified_unlabeled",
    "file_name": "log_0030_battery_failsafe.bin",
    "source_path": "downloads/log_0030_battery_failsafe.bin",
    "source_relative_path": "downloads/log_0030_battery_failsafe.bin",
    "size_bytes": 15912960,
    "sha256": "200022930ad7a751ae5777cda44b984019978f4847616c6fd1b19ee1872b0c93",
    "duplicate_count": 1,
    "duplicate_sources": [
      "downloads/log_0030_battery_failsafe.bin"
    ],
    "raw_label": "BATTERY_FAILSAFE",
    "mapped_label": "",
    "trainable": false,
    "source_type": "ArduPilot_Discuss",
    "source_url": "https://discuss.ardupilot.org/t/copter-3-5-5-rc1-available-for-beta-testing/25162",
    "resolved_download_url": "https://www.dropbox.com/s/6o48ttcpchowrwc/2018-01-28%2014-22-12.bin?dl=1",
    "provenance_status": "downloaded",
    "provenance_records": [
      {
        "manifest": "crawler_manifest.csv",
        "status": "downloaded",
        "label_raw": "BATTERY_FAILSAFE",
        "source_type": "ArduPilot_Discuss",
        "thread_url": "https://discuss.ardupilot.org/t/copter-3-5-5-rc1-available-for-beta-testing/25162",
        "resolved_url": "https://www.dropbox.com/s/6o48ttcpchowrwc/2018-01-28%2014-22-12.bin?dl=1"
      },
      {
        "manifest": "crawler_manifest_v2.csv",
        "status": "downloaded",
        "label_raw": "BATTERY_FAILSAFE",
        "source_type": "ArduPilot_Discuss",
        "thread_url": "https://discuss.ardupilot.org/t/copter-3-5-5-rc1-available-for-beta-testing/25162",
        "resolved_url": "https://www.dropbox.com/s/6o48ttcpchowrwc/2018-01-28%2014-22-12.bin?dl=1"
      }
    ],
    "expert_username": "rmackay9",
    "expert_quote": "Keith, There was a transmitter/receiver/RC failsafe in the log. I suspect that was what caused the RTL\u2026 A the risk of being nitpicky\u2026 the GCS almost never sends flight mode change requests, certainly it\u2019s not responsible for failsafes. In general the only time the GCSs request flight mode changes is when the user requests \u201cFollow-me\u201d, \u201cFly to Here\u201d or specifically hits one of the set-mode buttons (i.e. on the MP\u2019s ac",
    "parse_message_count": 3000,
    "parse_message_types": 50
  },
  {
    "category": "verified_unlabeled",
    "file_name": "log_0061_flyaway.bin",
    "source_path": "downloads/log_0061_flyaway.bin",
    "source_relative_path": "downloads/log_0061_flyaway.bin",
    "size_bytes": 536576,
    "sha256": "20fe2a41c6ded85bcc36efd3337de6bf53a5c0e0a8178d481f1ecc52bb38b18e",
    "duplicate_count": 1,
    "duplicate_sources": [
      "downloads/log_0061_flyaway.bin"
    ],
    "raw_label": "FLYAWAY",
    "mapped_label": "",
    "trainable": false,
    "source_type": "ArduPilot_Discuss",
    "source_url": "https://discuss.ardupilot.org/t/multiple-flyaways-in-loiter-and-auto/17663",
    "resolved_download_url": "https://discuss.ardupilot.org/uploads/default/original/2X/f/f40266d37d21bf5fbd884a2df41d7493bba06501.bin",
    "provenance_status": "downloaded",
    "provenance_records": [
      {
        "manifest": "crawler_manifest.csv",
        "status": "downloaded",
        "label_raw": "FLYAWAY",
        "source_type": "ArduPilot_Discuss",
        "thread_url": "https://discuss.ardupilot.org/t/multiple-flyaways-in-loiter-and-auto/17663",
        "resolved_url": "https://discuss.ardupilot.org/uploads/default/original/2X/f/f40266d37d21bf5fbd884a2df41d7493bba06501.bin"
      },
      {
        "manifest": "crawler_manifest_v2.csv",
        "status": "downloaded",
        "label_raw": "FLYAWAY",
        "source_type": "ArduPilot_Discuss",
        "thread_url": "https://discuss.ardupilot.org/t/multiple-flyaways-in-loiter-and-auto/17663",
        "resolved_url": "https://discuss.ardupilot.org/uploads/default/original/2X/f/f40266d37d21bf5fbd884a2df41d7493bba06501.bin"
      }
    ],
    "expert_username": "",
    "expert_quote": "",
    "parse_message_count": 3000,
    "parse_message_types": 36
  },
  {
    "category": "verified_unlabeled",
    "file_name": "log_0058_flyaway.bin",
    "source_path": "downloads/log_0058_flyaway.bin",
    "source_relative_path": "downloads/log_0058_flyaway.bin",
    "size_bytes": 1957888,
    "sha256": "396bc7ab6056c96abab9d93d615115f58c30e36a6a373565bd26e30b34cc057e",
    "duplicate_count": 1,
    "duplicate_sources": [
      "downloads/log_0058_flyaway.bin"
    ],
    "raw_label": "FLYAWAY",
    "mapped_label": "",
    "trainable": false,
    "source_type": "ArduPilot_Discuss",
    "source_url": "https://discuss.ardupilot.org/t/multiple-flyaways-in-guided-do-i-need-to-tune-the-ekf/17438",
    "resolved_download_url": "https://discuss.ardupilot.org/uploads/default/original/2X/5/5c5e9d4eb701803e566ba8cff6bba56fa5349499.bin",
    "provenance_status": "downloaded",
    "provenance_records": [
      {
        "manifest": "crawler_manifest.csv",
        "status": "downloaded",
        "label_raw": "FLYAWAY",
        "source_type": "ArduPilot_Discuss",
        "thread_url": "https://discuss.ardupilot.org/t/multiple-flyaways-in-guided-do-i-need-to-tune-the-ekf/17438",
        "resolved_url": "https://discuss.ardupilot.org/uploads/default/original/2X/5/5c5e9d4eb701803e566ba8cff6bba56fa5349499.bin"
      },
      {
        "manifest": "crawler_manifest_v2.csv",
        "status": "downloaded",
        "label_raw": "FLYAWAY",
        "source_type": "ArduPilot_Discuss",
        "thread_url": "https://discuss.ardupilot.org/t/multiple-flyaways-in-guided-do-i-need-to-tune-the-ekf/17438",
        "resolved_url": "https://discuss.ardupilot.org/uploads/default/original/2X/5/5c5e9d4eb701803e566ba8cff6bba56fa5349499.bin"
      }
    ],
    "expert_username": "",
    "expert_quote": "",
    "parse_message_count": 3000,
    "parse_message_types": 28
  },
  {
    "category": "verified_labeled",
    "file_name": "log_0044_mechanical_failure.bin",
    "source_path": "downloads/log_0044_mechanical_failure.bin",
    "source_relative_path": "downloads/log_0044_mechanical_failure.bin",
    "size_bytes": 9555968,
    "sha256": "405c8b855f571cfb58f800bb46723ff38732305f8c0e81a7d2d713feeade27bf",
    "duplicate_count": 1,
    "duplicate_sources": [
      "downloads/log_0044_mechanical_failure.bin"
    ],
    "raw_label": "MECHANICAL_FAILURE",
    "mapped_label": "mechanical_failure",
    "trainable": true,
    "source_type": "ArduPilot_Discuss",
    "source_url": "https://discuss.ardupilot.org/t/fixed-wing-dead-reckoning-test-of-the-zealot-h743-aero-applications-edition/101680",
    "resolved_download_url": "https://www.dropbox.com/s/k3wwb456zmd4454/log_69_UnknownDate.bin?dl=1",
    "provenance_status": "downloaded",
    "provenance_records": [
      {
        "manifest": "crawler_manifest.csv",
        "status": "downloaded",
        "label_raw": "MECHANICAL_FAILURE",
        "source_type": "ArduPilot_Discuss",
        "thread_url": "https://discuss.ardupilot.org/t/fixed-wing-dead-reckoning-test-of-the-zealot-h743-aero-applications-edition/101680",
        "resolved_url": "https://www.dropbox.com/s/k3wwb456zmd4454/log_69_UnknownDate.bin?dl=1"
      },
      {
        "manifest": "crawler_manifest_v2.csv",
        "status": "downloaded",
        "label_raw": "MECHANICAL_FAILURE",
        "source_type": "ArduPilot_Discuss",
        "thread_url": "https://discuss.ardupilot.org/t/fixed-wing-dead-reckoning-test-of-the-zealot-h743-aero-applications-edition/101680",
        "resolved_url": "https://www.dropbox.com/s/k3wwb456zmd4454/log_69_UnknownDate.bin?dl=1"
      }
    ],
    "expert_username": "timtuxworth",
    "expert_quote": "I plan to test dead reckoning using intertial navigation on the Qio-Tek Zealot H743 \u201cAero Applications Edition\u201d which has an IIM-42652, ICM-42688P and an ADIS\u201316470 IMU. Also: Barometers: DPS3018 *2 Compass: QMC5883L I\u2019ll also install an ASP-5033 Airspeed sensor (using DroneCAN of course). I know I can \u201cdisable\u201d GPS in software, but call me cynical, I want to be 100% sure that while flying with no GPS, there is no ch",
    "parse_message_count": 3000,
    "parse_message_types": 59
  },
  {
    "category": "verified_unlabeled",
    "file_name": "log_0032_hardware_failure.bin",
    "source_path": "downloads/log_0032_hardware_failure.bin",
    "source_relative_path": "downloads/log_0032_hardware_failure.bin",
    "size_bytes": 51604795,
    "sha256": "476a5e4c28ef03599353736a46d832d0a14193e5ea3b28246aea6bc945c529ef",
    "duplicate_count": 1,
    "duplicate_sources": [
      "downloads/log_0032_hardware_failure.bin"
    ],
    "raw_label": "HARDWARE_FAILURE",
    "mapped_label": "",
    "trainable": false,
    "source_type": "ArduPilot_Discuss",
    "source_url": "https://discuss.ardupilot.org/t/failure-to-launch/80437",
    "resolved_download_url": "https://www.dropbox.com/s/b4ebs8bgc4wfthx/2021-12-31.BIN?dl=1",
    "provenance_status": "downloaded",
    "provenance_records": [
      {
        "manifest": "crawler_manifest.csv",
        "status": "downloaded",
        "label_raw": "HARDWARE_FAILURE",
        "source_type": "ArduPilot_Discuss",
        "thread_url": "https://discuss.ardupilot.org/t/failure-to-launch/80437",
        "resolved_url": "https://www.dropbox.com/s/b4ebs8bgc4wfthx/2021-12-31.BIN?dl=1"
      },
      {
        "manifest": "crawler_manifest_v2.csv",
        "status": "downloaded",
        "label_raw": "HARDWARE_FAILURE",
        "source_type": "ArduPilot_Discuss",
        "thread_url": "https://discuss.ardupilot.org/t/failure-to-launch/80437",
        "resolved_url": "https://www.dropbox.com/s/b4ebs8bgc4wfthx/2021-12-31.BIN?dl=1"
      }
    ],
    "expert_username": "timtuxworth",
    "expert_quote": "I\u2019ve recently experienced some odd takeoff behaviour with my Bixinator. I have everything setup for auto launch in my Mission, I arm the plane and throw it and some random (apparently) percentage of the time the motor doesn\u2019t fire and it just glides to the ground. If I reset the mission and try again, it sometimes works. Or sometimes it works the first time. I haven\u2019t been able to figure out what I\u2019m doing wrong. Thi",
    "parse_message_count": 3000,
    "parse_message_types": 52
  },
  {
    "category": "verified_unlabeled",
    "file_name": "log_0063_flyaway.bin",
    "source_path": "downloads/log_0063_flyaway.bin",
    "source_relative_path": "downloads/log_0063_flyaway.bin",
    "size_bytes": 19991073,
    "sha256": "4be9cde3ea55c3cdabf84251ec2064591d051c71b6a4c973760ca65202e1ce40",
    "duplicate_count": 1,
    "duplicate_sources": [
      "downloads/log_0063_flyaway.bin"
    ],
    "raw_label": "FLYAWAY",
    "mapped_label": "",
    "trainable": false,
    "source_type": "ArduPilot_Discuss",
    "source_url": "https://discuss.ardupilot.org/t/possibly-a-fly-away-please-take-a-look-at-the-log/41183",
    "resolved_download_url": "https://www.dropbox.com/s/3510estj2dtc6ri/2019-04-11%2013-03-43.bin?dl=1",
    "provenance_status": "downloaded",
    "provenance_records": [
      {
        "manifest": "crawler_manifest.csv",
        "status": "downloaded",
        "label_raw": "FLYAWAY",
        "source_type": "ArduPilot_Discuss",
        "thread_url": "https://discuss.ardupilot.org/t/possibly-a-fly-away-please-take-a-look-at-the-log/41183",
        "resolved_url": "https://www.dropbox.com/s/3510estj2dtc6ri/2019-04-11%2013-03-43.bin?dl=1"
      },
      {
        "manifest": "crawler_manifest_v2.csv",
        "status": "downloaded",
        "label_raw": "FLYAWAY",
        "source_type": "ArduPilot_Discuss",
        "thread_url": "https://discuss.ardupilot.org/t/possibly-a-fly-away-please-take-a-look-at-the-log/41183",
        "resolved_url": "https://www.dropbox.com/s/3510estj2dtc6ri/2019-04-11%2013-03-43.bin?dl=1"
      }
    ],
    "expert_username": "",
    "expert_quote": "",
    "parse_message_count": 3000,
    "parse_message_types": 53
  },
  {
    "category": "verified_unlabeled",
    "file_name": "log_0054_oscillation_crash.bin",
    "source_path": "downloads/log_0054_oscillation_crash.bin",
    "source_relative_path": "downloads/log_0054_oscillation_crash.bin",
    "size_bytes": 14000201,
    "sha256": "5429897d5ff19a109ff8a5ae95a09e63a21d97b976cb36d35cfd31d114ddf55d",
    "duplicate_count": 1,
    "duplicate_sources": [
      "downloads/log_0054_oscillation_crash.bin"
    ],
    "raw_label": "OSCILLATION_CRASH",
    "mapped_label": "",
    "trainable": false,
    "source_type": "ArduPilot_Discuss",
    "source_url": "https://discuss.ardupilot.org/t/tuning-issues-with-plane-successful-auto-t-o-and-land-maiden-now-not-so-much/100608",
    "resolved_download_url": "https://www.dropbox.com/s/mlu04lxc5bmp9fu/2023-05-06%20Sortie%203.bin?dl=1",
    "provenance_status": "downloaded",
    "provenance_records": [
      {
        "manifest": "crawler_manifest.csv",
        "status": "downloaded",
        "label_raw": "OSCILLATION_CRASH",
        "source_type": "ArduPilot_Discuss",
        "thread_url": "https://discuss.ardupilot.org/t/tuning-issues-with-plane-successful-auto-t-o-and-land-maiden-now-not-so-much/100608",
        "resolved_url": "https://www.dropbox.com/s/mlu04lxc5bmp9fu/2023-05-06%20Sortie%203.bin?dl=1"
      },
      {
        "manifest": "crawler_manifest_v2.csv",
        "status": "downloaded",
        "label_raw": "OSCILLATION_CRASH",
        "source_type": "ArduPilot_Discuss",
        "thread_url": "https://discuss.ardupilot.org/t/tuning-issues-with-plane-successful-auto-t-o-and-land-maiden-now-not-so-much/100608",
        "resolved_url": "https://www.dropbox.com/s/mlu04lxc5bmp9fu/2023-05-06%20Sortie%203.bin?dl=1"
      }
    ],
    "expert_username": "",
    "expert_quote": "",
    "parse_message_count": 3000,
    "parse_message_types": 51
  },
  {
    "category": "verified_labeled",
    "file_name": "log_0040_mechanical_failure.bin",
    "source_path": "downloads/log_0040_mechanical_failure.bin",
    "source_relative_path": "downloads/log_0040_mechanical_failure.bin",
    "size_bytes": 6467478,
    "sha256": "58f3f3b631233a6dc4c20f6d42ed47252d0c05788bd45fd57fc87074bad68778",
    "duplicate_count": 1,
    "duplicate_sources": [
      "downloads/log_0040_mechanical_failure.bin"
    ],
    "raw_label": "MECHANICAL_FAILURE",
    "mapped_label": "mechanical_failure",
    "trainable": true,
    "source_type": "ArduPilot_Discuss",
    "source_url": "https://discuss.ardupilot.org/t/engine-failure-bug-mechanical-or-other/77323",
    "resolved_download_url": "https://www.dropbox.com/s/wllzkuniarpydez/00000035.bin?dl=1",
    "provenance_status": "downloaded",
    "provenance_records": [
      {
        "manifest": "crawler_manifest.csv",
        "status": "downloaded",
        "label_raw": "MECHANICAL_FAILURE",
        "source_type": "ArduPilot_Discuss",
        "thread_url": "https://discuss.ardupilot.org/t/engine-failure-bug-mechanical-or-other/77323",
        "resolved_url": "https://www.dropbox.com/s/wllzkuniarpydez/00000035.bin?dl=1"
      },
      {
        "manifest": "crawler_manifest_v2.csv",
        "status": "downloaded",
        "label_raw": "MECHANICAL_FAILURE",
        "source_type": "ArduPilot_Discuss",
        "thread_url": "https://discuss.ardupilot.org/t/engine-failure-bug-mechanical-or-other/77323",
        "resolved_url": "https://www.dropbox.com/s/wllzkuniarpydez/00000035.bin?dl=1"
      }
    ],
    "expert_username": "",
    "expert_quote": "",
    "parse_message_count": 3000,
    "parse_message_types": 48
  },
  {
    "category": "verified_unlabeled",
    "file_name": "log_0055_oscillation_crash.bin",
    "source_path": "downloads/log_0055_oscillation_crash.bin",
    "source_relative_path": "downloads/log_0055_oscillation_crash.bin",
    "size_bytes": 6864896,
    "sha256": "744e1d163202c8578dae7aca509430972ddd8e0f6ce402d9d2a94ed5e329a339",
    "duplicate_count": 1,
    "duplicate_sources": [
      "downloads/log_0055_oscillation_crash.bin"
    ],
    "raw_label": "OSCILLATION_CRASH",
    "mapped_label": "",
    "trainable": false,
    "source_type": "ArduPilot_Discuss",
    "source_url": "https://discuss.ardupilot.org/t/tuning-issues-with-plane-successful-auto-t-o-and-land-maiden-now-not-so-much/100608",
    "resolved_download_url": "https://www.dropbox.com/s/rzg3oqs3gjo8pyg/2023-05-07%2009-43-52.bin?dl=1",
    "provenance_status": "downloaded",
    "provenance_records": [
      {
        "manifest": "crawler_manifest.csv",
        "status": "downloaded",
        "label_raw": "OSCILLATION_CRASH",
        "source_type": "ArduPilot_Discuss",
        "thread_url": "https://discuss.ardupilot.org/t/tuning-issues-with-plane-successful-auto-t-o-and-land-maiden-now-not-so-much/100608",
        "resolved_url": "https://www.dropbox.com/s/rzg3oqs3gjo8pyg/2023-05-07%2009-43-52.bin?dl=1"
      },
      {
        "manifest": "crawler_manifest_v2.csv",
        "status": "downloaded",
        "label_raw": "OSCILLATION_CRASH",
        "source_type": "ArduPilot_Discuss",
        "thread_url": "https://discuss.ardupilot.org/t/tuning-issues-with-plane-successful-auto-t-o-and-land-maiden-now-not-so-much/100608",
        "resolved_url": "https://www.dropbox.com/s/rzg3oqs3gjo8pyg/2023-05-07%2009-43-52.bin?dl=1"
      }
    ],
    "expert_username": "",
    "expert_quote": "",
    "parse_message_count": 3000,
    "parse_message_types": 55
  },
  {
    "category": "verified_labeled",
    "file_name": "log_0045_mechanical_failure.bin",
    "source_path": "downloads/log_0045_mechanical_failure.bin",
    "source_relative_path": "downloads/log_0045_mechanical_failure.bin",
    "size_bytes": 34263040,
    "sha256": "75a2881bbec319096c2ee9bd40881910f70fcfed759995dc39f8147656602699",
    "duplicate_count": 1,
    "duplicate_sources": [
      "downloads/log_0045_mechanical_failure.bin"
    ],
    "raw_label": "MECHANICAL_FAILURE",
    "mapped_label": "mechanical_failure",
    "trainable": true,
    "source_type": "ArduPilot_Discuss",
    "source_url": "https://discuss.ardupilot.org/t/fixed-wing-dead-reckoning-test-of-the-zealot-h743-aero-applications-edition/101680",
    "resolved_download_url": "https://www.dropbox.com/s/0wye5b2luz6uxys/log_70_UnknownDate.bin?dl=1",
    "provenance_status": "downloaded",
    "provenance_records": [
      {
        "manifest": "crawler_manifest.csv",
        "status": "downloaded",
        "label_raw": "MECHANICAL_FAILURE",
        "source_type": "ArduPilot_Discuss",
        "thread_url": "https://discuss.ardupilot.org/t/fixed-wing-dead-reckoning-test-of-the-zealot-h743-aero-applications-edition/101680",
        "resolved_url": "https://www.dropbox.com/s/0wye5b2luz6uxys/log_70_UnknownDate.bin?dl=1"
      },
      {
        "manifest": "crawler_manifest_v2.csv",
        "status": "downloaded",
        "label_raw": "MECHANICAL_FAILURE",
        "source_type": "ArduPilot_Discuss",
        "thread_url": "https://discuss.ardupilot.org/t/fixed-wing-dead-reckoning-test-of-the-zealot-h743-aero-applications-edition/101680",
        "resolved_url": "https://www.dropbox.com/s/0wye5b2luz6uxys/log_70_UnknownDate.bin?dl=1"
      }
    ],
    "expert_username": "timtuxworth",
    "expert_quote": "I plan to test dead reckoning using intertial navigation on the Qio-Tek Zealot H743 \u201cAero Applications Edition\u201d which has an IIM-42652, ICM-42688P and an ADIS\u201316470 IMU. Also: Barometers: DPS3018 *2 Compass: QMC5883L I\u2019ll also install an ASP-5033 Airspeed sensor (using DroneCAN of course). I know I can \u201cdisable\u201d GPS in software, but call me cynical, I want to be 100% sure that while flying with no GPS, there is no ch",
    "parse_message_count": 3000,
    "parse_message_types": 59
  },
  {
    "category": "verified_unlabeled",
    "file_name": "log_0071_radio_failsafe.bin",
    "source_path": "downloads/log_0071_radio_failsafe.bin",
    "source_relative_path": "downloads/log_0071_radio_failsafe.bin",
    "size_bytes": 937984,
    "sha256": "7b4e98a4d20fd3ec5325b0b6a964112b7a4cc8f5b3e6e1d6a4cd36a5f441a942",
    "duplicate_count": 1,
    "duplicate_sources": [
      "downloads/log_0071_radio_failsafe.bin"
    ],
    "raw_label": "RADIO_FAILSAFE",
    "mapped_label": "",
    "trainable": false,
    "source_type": "ArduPilot_Discuss",
    "source_url": "https://discuss.ardupilot.org/t/failsafe-sbus-not-working/65942",
    "resolved_download_url": "https://discuss.ardupilot.org/uploads/short-url/vG7jGvly6GczEcqhB9qDhcFrOdo.bin",
    "provenance_status": "downloaded",
    "provenance_records": [
      {
        "manifest": "crawler_manifest.csv",
        "status": "downloaded",
        "label_raw": "RADIO_FAILSAFE",
        "source_type": "ArduPilot_Discuss",
        "thread_url": "https://discuss.ardupilot.org/t/failsafe-sbus-not-working/65942",
        "resolved_url": "https://discuss.ardupilot.org/uploads/short-url/vG7jGvly6GczEcqhB9qDhcFrOdo.bin"
      },
      {
        "manifest": "crawler_manifest_v2.csv",
        "status": "downloaded",
        "label_raw": "RADIO_FAILSAFE",
        "source_type": "ArduPilot_Discuss",
        "thread_url": "https://discuss.ardupilot.org/t/failsafe-sbus-not-working/65942",
        "resolved_url": "https://discuss.ardupilot.org/uploads/short-url/vG7jGvly6GczEcqhB9qDhcFrOdo.bin"
      }
    ],
    "expert_username": "xfacta",
    "expert_quote": "Yes that\u2019s the same as what I get. I have just bound a new receiver (during very low throttle) and Taranis is set to No Pulses. I\u2019m using ArduCopter V4.0.5 on this quad. Arducopter realises there\u2019s no pulses (PWM or SBUS) from the receiver and enters failsafe, same as if the throttle channel goes below the set PWM level. I have a throttle disable switch SF set to drop the throttle channel to 930 PWM or there-about. W",
    "parse_message_count": 3000,
    "parse_message_types": 45
  },
  {
    "category": "verified_unlabeled",
    "file_name": "log_0028_battery_failsafe.bin",
    "source_path": "downloads/log_0028_battery_failsafe.bin",
    "source_relative_path": "downloads/log_0028_battery_failsafe.bin",
    "size_bytes": 3062925,
    "sha256": "8edac767be66c882f4374171331c5f6d90114d82757fb59bb15abb171918df9a",
    "duplicate_count": 1,
    "duplicate_sources": [
      "downloads/log_0028_battery_failsafe.bin"
    ],
    "raw_label": "BATTERY_FAILSAFE",
    "mapped_label": "",
    "trainable": false,
    "source_type": "ArduPilot_Discuss",
    "source_url": "https://discuss.ardupilot.org/t/rtl-does-not-return-to-launch-nor-lands-but-kind-of-loiters/6876",
    "resolved_download_url": "https://discuss.ardupilot.org/uploads/default/original/2X/4/4f5f3c6890c8bbc195df1e3a47e3e48fd82f5626.bin",
    "provenance_status": "downloaded",
    "provenance_records": [
      {
        "manifest": "crawler_manifest.csv",
        "status": "downloaded",
        "label_raw": "BATTERY_FAILSAFE",
        "source_type": "ArduPilot_Discuss",
        "thread_url": "https://discuss.ardupilot.org/t/rtl-does-not-return-to-launch-nor-lands-but-kind-of-loiters/6876",
        "resolved_url": "https://discuss.ardupilot.org/uploads/default/original/2X/4/4f5f3c6890c8bbc195df1e3a47e3e48fd82f5626.bin"
      },
      {
        "manifest": "crawler_manifest_v2.csv",
        "status": "downloaded",
        "label_raw": "BATTERY_FAILSAFE",
        "source_type": "ArduPilot_Discuss",
        "thread_url": "https://discuss.ardupilot.org/t/rtl-does-not-return-to-launch-nor-lands-but-kind-of-loiters/6876",
        "resolved_url": "https://discuss.ardupilot.org/uploads/default/original/2X/4/4f5f3c6890c8bbc195df1e3a47e3e48fd82f5626.bin"
      }
    ],
    "expert_username": "",
    "expert_quote": "",
    "parse_message_count": 3000,
    "parse_message_types": 39
  },
  {
    "category": "verified_unlabeled",
    "file_name": "log_0056_oscillation_crash.bin",
    "source_path": "downloads/log_0056_oscillation_crash.bin",
    "source_relative_path": "downloads/log_0056_oscillation_crash.bin",
    "size_bytes": 27369390,
    "sha256": "96fb229fb404f57bc4d1c4ed4b41da69a6d442a618fdae1d3208b5d9fe425b69",
    "duplicate_count": 1,
    "duplicate_sources": [
      "downloads/log_0056_oscillation_crash.bin"
    ],
    "raw_label": "OSCILLATION_CRASH",
    "mapped_label": "",
    "trainable": false,
    "source_type": "ArduPilot_Discuss",
    "source_url": "https://discuss.ardupilot.org/t/crash-when-switching-from-rtl-to-loiter/103732",
    "resolved_download_url": "https://www.dropbox.com/s/uxdm6xycvbdawi1/00000020.BIN?dl=1",
    "provenance_status": "downloaded",
    "provenance_records": [
      {
        "manifest": "crawler_manifest.csv",
        "status": "downloaded",
        "label_raw": "OSCILLATION_CRASH",
        "source_type": "ArduPilot_Discuss",
        "thread_url": "https://discuss.ardupilot.org/t/crash-when-switching-from-rtl-to-loiter/103732",
        "resolved_url": "https://www.dropbox.com/s/uxdm6xycvbdawi1/00000020.BIN?dl=1"
      },
      {
        "manifest": "crawler_manifest_v2.csv",
        "status": "downloaded",
        "label_raw": "OSCILLATION_CRASH",
        "source_type": "ArduPilot_Discuss",
        "thread_url": "https://discuss.ardupilot.org/t/crash-when-switching-from-rtl-to-loiter/103732",
        "resolved_url": "https://www.dropbox.com/s/uxdm6xycvbdawi1/00000020.BIN?dl=1"
      }
    ],
    "expert_username": "",
    "expert_quote": "",
    "parse_message_count": 3000,
    "parse_message_types": 53
  },
  {
    "category": "verified_unlabeled",
    "file_name": "log_0059_flyaway.bin",
    "source_path": "downloads/log_0059_flyaway.bin",
    "source_relative_path": "downloads/log_0059_flyaway.bin",
    "size_bytes": 489031,
    "sha256": "9ae5224970cc1340f99205a1ef807742470924352a68e606e13d0c249f6bef51",
    "duplicate_count": 1,
    "duplicate_sources": [
      "downloads/log_0059_flyaway.bin"
    ],
    "raw_label": "FLYAWAY",
    "mapped_label": "",
    "trainable": false,
    "source_type": "ArduPilot_Discuss",
    "source_url": "https://discuss.ardupilot.org/t/something-is-wrong-with-my-copter-build/46289",
    "resolved_download_url": "https://discuss.ardupilot.org/uploads/default/original/3X/4/4/44c19152db50fffa82ba24cd744884ae0fa7cc78.BIN",
    "provenance_status": "downloaded",
    "provenance_records": [
      {
        "manifest": "crawler_manifest.csv",
        "status": "downloaded",
        "label_raw": "FLYAWAY",
        "source_type": "ArduPilot_Discuss",
        "thread_url": "https://discuss.ardupilot.org/t/something-is-wrong-with-my-copter-build/46289",
        "resolved_url": "https://discuss.ardupilot.org/uploads/default/original/3X/4/4/44c19152db50fffa82ba24cd744884ae0fa7cc78.BIN"
      },
      {
        "manifest": "crawler_manifest_v2.csv",
        "status": "downloaded",
        "label_raw": "FLYAWAY",
        "source_type": "ArduPilot_Discuss",
        "thread_url": "https://discuss.ardupilot.org/t/something-is-wrong-with-my-copter-build/46289",
        "resolved_url": "https://discuss.ardupilot.org/uploads/default/original/3X/4/4/44c19152db50fffa82ba24cd744884ae0fa7cc78.BIN"
      }
    ],
    "expert_username": "",
    "expert_quote": "",
    "parse_message_count": 3000,
    "parse_message_types": 48
  },
  {
    "category": "verified_unlabeled",
    "file_name": "log_0060_flyaway.bin",
    "source_path": "downloads/log_0060_flyaway.bin",
    "source_relative_path": "downloads/log_0060_flyaway.bin",
    "size_bytes": 444767,
    "sha256": "a4d4a24d39c3a028704f0cee08899d60c46ba43ed237662b2352fdf8d02fe0a4",
    "duplicate_count": 1,
    "duplicate_sources": [
      "downloads/log_0060_flyaway.bin"
    ],
    "raw_label": "FLYAWAY",
    "mapped_label": "",
    "trainable": false,
    "source_type": "ArduPilot_Discuss",
    "source_url": "https://discuss.ardupilot.org/t/something-is-wrong-with-my-copter-build/46289",
    "resolved_download_url": "https://discuss.ardupilot.org/uploads/default/original/3X/c/1/c1c307f08b658727f8f74151d1f141be0ee663e4.BIN",
    "provenance_status": "downloaded",
    "provenance_records": [
      {
        "manifest": "crawler_manifest.csv",
        "status": "downloaded",
        "label_raw": "FLYAWAY",
        "source_type": "ArduPilot_Discuss",
        "thread_url": "https://discuss.ardupilot.org/t/something-is-wrong-with-my-copter-build/46289",
        "resolved_url": "https://discuss.ardupilot.org/uploads/default/original/3X/c/1/c1c307f08b658727f8f74151d1f141be0ee663e4.BIN"
      },
      {
        "manifest": "crawler_manifest_v2.csv",
        "status": "downloaded",
        "label_raw": "FLYAWAY",
        "source_type": "ArduPilot_Discuss",
        "thread_url": "https://discuss.ardupilot.org/t/something-is-wrong-with-my-copter-build/46289",
        "resolved_url": "https://discuss.ardupilot.org/uploads/default/original/3X/c/1/c1c307f08b658727f8f74151d1f141be0ee663e4.BIN"
      }
    ],
    "expert_username": "",
    "expert_quote": "",
    "parse_message_count": 3000,
    "parse_message_types": 48
  },
  {
    "category": "verified_labeled",
    "file_name": "log_0043_mechanical_failure.bin",
    "source_path": "downloads/log_0043_mechanical_failure.bin",
    "source_relative_path": "downloads/log_0043_mechanical_failure.bin",
    "size_bytes": 44539904,
    "sha256": "aac514db54f5aedc3af338ba5a94d3a5369ae4ecf33f96d0f4692b83f93fa253",
    "duplicate_count": 1,
    "duplicate_sources": [
      "downloads/log_0043_mechanical_failure.bin"
    ],
    "raw_label": "MECHANICAL_FAILURE",
    "mapped_label": "mechanical_failure",
    "trainable": true,
    "source_type": "ArduPilot_Discuss",
    "source_url": "https://discuss.ardupilot.org/t/fixed-wing-dead-reckoning-test-of-the-zealot-h743-aero-applications-edition/101680",
    "resolved_download_url": "https://www.dropbox.com/s/zfv5a8i0rx6ce3w/log_57_UnknownDate.bin?dl=1",
    "provenance_status": "downloaded",
    "provenance_records": [
      {
        "manifest": "crawler_manifest.csv",
        "status": "downloaded",
        "label_raw": "MECHANICAL_FAILURE",
        "source_type": "ArduPilot_Discuss",
        "thread_url": "https://discuss.ardupilot.org/t/fixed-wing-dead-reckoning-test-of-the-zealot-h743-aero-applications-edition/101680",
        "resolved_url": "https://www.dropbox.com/s/zfv5a8i0rx6ce3w/log_57_UnknownDate.bin?dl=1"
      },
      {
        "manifest": "crawler_manifest_v2.csv",
        "status": "downloaded",
        "label_raw": "MECHANICAL_FAILURE",
        "source_type": "ArduPilot_Discuss",
        "thread_url": "https://discuss.ardupilot.org/t/fixed-wing-dead-reckoning-test-of-the-zealot-h743-aero-applications-edition/101680",
        "resolved_url": "https://www.dropbox.com/s/zfv5a8i0rx6ce3w/log_57_UnknownDate.bin?dl=1"
      }
    ],
    "expert_username": "timtuxworth",
    "expert_quote": "I plan to test dead reckoning using intertial navigation on the Qio-Tek Zealot H743 \u201cAero Applications Edition\u201d which has an IIM-42652, ICM-42688P and an ADIS\u201316470 IMU. Also: Barometers: DPS3018 *2 Compass: QMC5883L I\u2019ll also install an ASP-5033 Airspeed sensor (using DroneCAN of course). I know I can \u201cdisable\u201d GPS in software, but call me cynical, I want to be 100% sure that while flying with no GPS, there is no ch",
    "parse_message_count": 3000,
    "parse_message_types": 57
  },
  {
    "category": "verified_unlabeled",
    "file_name": "log_0066_flyaway.bin",
    "source_path": "downloads/log_0066_flyaway.bin",
    "source_relative_path": "downloads/log_0066_flyaway.bin",
    "size_bytes": 471040,
    "sha256": "af2836cad8f18ca67758f6e45730a2756a37938dfc2f2e2dc6fbb27dca7e5641",
    "duplicate_count": 1,
    "duplicate_sources": [
      "downloads/log_0066_flyaway.bin"
    ],
    "raw_label": "FLYAWAY",
    "mapped_label": "",
    "trainable": false,
    "source_type": "ArduPilot_Discuss",
    "source_url": "https://discuss.ardupilot.org/t/radio-failsafe-during-operation/101055",
    "resolved_download_url": "https://discuss.ardupilot.org/uploads/short-url/sB75zhLsNHbvwByMRs0nPqaLtMl.bin",
    "provenance_status": "downloaded",
    "provenance_records": [
      {
        "manifest": "crawler_manifest.csv",
        "status": "downloaded",
        "label_raw": "FLYAWAY",
        "source_type": "ArduPilot_Discuss",
        "thread_url": "https://discuss.ardupilot.org/t/radio-failsafe-during-operation/101055",
        "resolved_url": "https://discuss.ardupilot.org/uploads/short-url/sB75zhLsNHbvwByMRs0nPqaLtMl.bin"
      },
      {
        "manifest": "crawler_manifest_v2.csv",
        "status": "downloaded",
        "label_raw": "FLYAWAY",
        "source_type": "ArduPilot_Discuss",
        "thread_url": "https://discuss.ardupilot.org/t/radio-failsafe-during-operation/101055",
        "resolved_url": "https://discuss.ardupilot.org/uploads/short-url/sB75zhLsNHbvwByMRs0nPqaLtMl.bin"
      }
    ],
    "expert_username": "xfacta",
    "expert_quote": "The altitude issue first It\u2019s likely these are too high MOT_SPIN_ARM,0.14 MOT_SPIN_MIN,0.17 MOT_THST_HOVER,0.5212066 Try these for a starting point MOT_SPIN_ARM,0.10 MOT_SPIN_MIN,0.13 MOT_THST_HOVER,0.2 Vibrations do rise and altitude goes up (which is a problem that can occur) but in your case it\u2019s hard to tell if the vibrations are a cause or symptom because of the short flight time and minimal good data. For testi",
    "parse_message_count": 3000,
    "parse_message_types": 47
  },
  {
    "category": "verified_unlabeled",
    "file_name": "log_0067_flyaway.bin",
    "source_path": "downloads/log_0067_flyaway.bin",
    "source_relative_path": "downloads/log_0067_flyaway.bin",
    "size_bytes": 1064960,
    "sha256": "b729efbac030e6071c1725cc8a06d7dbf37b7728f6f2f20c9cb805e1b893eacc",
    "duplicate_count": 1,
    "duplicate_sources": [
      "downloads/log_0067_flyaway.bin"
    ],
    "raw_label": "FLYAWAY",
    "mapped_label": "",
    "trainable": false,
    "source_type": "ArduPilot_Discuss",
    "source_url": "https://discuss.ardupilot.org/t/solo-flyaway-and-crash-during-auto-mission/15265",
    "resolved_download_url": "https://discuss.ardupilot.org/uploads/default/original/2X/1/1d6479371c10273c90252d5e8915d55d49e27d03.BIN",
    "provenance_status": "downloaded",
    "provenance_records": [
      {
        "manifest": "crawler_manifest.csv",
        "status": "downloaded",
        "label_raw": "FLYAWAY",
        "source_type": "ArduPilot_Discuss",
        "thread_url": "https://discuss.ardupilot.org/t/solo-flyaway-and-crash-during-auto-mission/15265",
        "resolved_url": "https://discuss.ardupilot.org/uploads/default/original/2X/1/1d6479371c10273c90252d5e8915d55d49e27d03.BIN"
      },
      {
        "manifest": "crawler_manifest_v2.csv",
        "status": "downloaded",
        "label_raw": "FLYAWAY",
        "source_type": "ArduPilot_Discuss",
        "thread_url": "https://discuss.ardupilot.org/t/solo-flyaway-and-crash-during-auto-mission/15265",
        "resolved_url": "https://discuss.ardupilot.org/uploads/default/original/2X/1/1d6479371c10273c90252d5e8915d55d49e27d03.BIN"
      }
    ],
    "expert_username": "",
    "expert_quote": "",
    "parse_message_count": 3000,
    "parse_message_types": 35
  },
  {
    "category": "verified_unlabeled",
    "file_name": "log_0065_flyaway.bin",
    "source_path": "downloads/log_0065_flyaway.bin",
    "source_relative_path": "downloads/log_0065_flyaway.bin",
    "size_bytes": 19783680,
    "sha256": "b89fc87fea657312f90ca28f92e6108f42bc97cb5c27267df8fc82bdfae690c0",
    "duplicate_count": 1,
    "duplicate_sources": [
      "downloads/log_0065_flyaway.bin"
    ],
    "raw_label": "FLYAWAY",
    "mapped_label": "",
    "trainable": false,
    "source_type": "ArduPilot_Discuss",
    "source_url": "https://discuss.ardupilot.org/t/radio-failsafe-during-operation/101055",
    "resolved_download_url": "https://www.dropbox.com/s/zmr1y91j84zsoa3/2023-05-11%2017-08-06%28Testing%29.bin?dl=1",
    "provenance_status": "downloaded",
    "provenance_records": [
      {
        "manifest": "crawler_manifest.csv",
        "status": "downloaded",
        "label_raw": "FLYAWAY",
        "source_type": "ArduPilot_Discuss",
        "thread_url": "https://discuss.ardupilot.org/t/radio-failsafe-during-operation/101055",
        "resolved_url": "https://www.dropbox.com/s/zmr1y91j84zsoa3/2023-05-11%2017-08-06%28Testing%29.bin?dl=1"
      },
      {
        "manifest": "crawler_manifest_v2.csv",
        "status": "downloaded",
        "label_raw": "FLYAWAY",
        "source_type": "ArduPilot_Discuss",
        "thread_url": "https://discuss.ardupilot.org/t/radio-failsafe-during-operation/101055",
        "resolved_url": "https://www.dropbox.com/s/zmr1y91j84zsoa3/2023-05-11%2017-08-06%28Testing%29.bin?dl=1"
      }
    ],
    "expert_username": "xfacta",
    "expert_quote": "The altitude issue first It\u2019s likely these are too high MOT_SPIN_ARM,0.14 MOT_SPIN_MIN,0.17 MOT_THST_HOVER,0.5212066 Try these for a starting point MOT_SPIN_ARM,0.10 MOT_SPIN_MIN,0.13 MOT_THST_HOVER,0.2 Vibrations do rise and altitude goes up (which is a problem that can occur) but in your case it\u2019s hard to tell if the vibrations are a cause or symptom because of the short flight time and minimal good data. For testi",
    "parse_message_count": 3000,
    "parse_message_types": 51
  },
  {
    "category": "verified_unlabeled",
    "file_name": "log_0052_oscillation_crash.bin",
    "source_path": "downloads/log_0052_oscillation_crash.bin",
    "source_relative_path": "downloads/log_0052_oscillation_crash.bin",
    "size_bytes": 28160553,
    "sha256": "b8d168d2f71525654f6737a6b2b1ec719de7655ba70415bca7c0ca921d0940e4",
    "duplicate_count": 1,
    "duplicate_sources": [
      "downloads/log_0052_oscillation_crash.bin"
    ],
    "raw_label": "OSCILLATION_CRASH",
    "mapped_label": "",
    "trainable": false,
    "source_type": "ArduPilot_Discuss",
    "source_url": "https://discuss.ardupilot.org/t/tuning-issues-with-plane-successful-auto-t-o-and-land-maiden-now-not-so-much/100608",
    "resolved_download_url": "https://www.dropbox.com/s/zbji6cslc9kwrip/2023-05-04%2007-51-33.bin?dl=1",
    "provenance_status": "downloaded",
    "provenance_records": [
      {
        "manifest": "crawler_manifest.csv",
        "status": "downloaded",
        "label_raw": "OSCILLATION_CRASH",
        "source_type": "ArduPilot_Discuss",
        "thread_url": "https://discuss.ardupilot.org/t/tuning-issues-with-plane-successful-auto-t-o-and-land-maiden-now-not-so-much/100608",
        "resolved_url": "https://www.dropbox.com/s/zbji6cslc9kwrip/2023-05-04%2007-51-33.bin?dl=1"
      },
      {
        "manifest": "crawler_manifest_v2.csv",
        "status": "downloaded",
        "label_raw": "OSCILLATION_CRASH",
        "source_type": "ArduPilot_Discuss",
        "thread_url": "https://discuss.ardupilot.org/t/tuning-issues-with-plane-successful-auto-t-o-and-land-maiden-now-not-so-much/100608",
        "resolved_url": "https://www.dropbox.com/s/zbji6cslc9kwrip/2023-05-04%2007-51-33.bin?dl=1"
      }
    ],
    "expert_username": "",
    "expert_quote": "",
    "parse_message_count": 3000,
    "parse_message_types": 54
  },
  {
    "category": "verified_unlabeled",
    "file_name": "log_0049_oscillation_crash.bin",
    "source_path": "downloads/log_0049_oscillation_crash.bin",
    "source_relative_path": "downloads/log_0049_oscillation_crash.bin",
    "size_bytes": 495616,
    "sha256": "bffc80e1da7d30ad042d9b8a0cdb06e01b0f1dbccae3589f415b1874502cb256",
    "duplicate_count": 1,
    "duplicate_sources": [
      "downloads/log_0049_oscillation_crash.bin"
    ],
    "raw_label": "OSCILLATION_CRASH",
    "mapped_label": "",
    "trainable": false,
    "source_type": "ArduPilot_Discuss",
    "source_url": "https://discuss.ardupilot.org/t/quadcopter-crash-log-analysis-request/99897",
    "resolved_download_url": "https://discuss.ardupilot.org/uploads/short-url/a0lX05vZi6e2DuMEbvII2z7DIU9.BIN",
    "provenance_status": "downloaded",
    "provenance_records": [
      {
        "manifest": "crawler_manifest.csv",
        "status": "downloaded",
        "label_raw": "OSCILLATION_CRASH",
        "source_type": "ArduPilot_Discuss",
        "thread_url": "https://discuss.ardupilot.org/t/quadcopter-crash-log-analysis-request/99897",
        "resolved_url": "https://discuss.ardupilot.org/uploads/short-url/a0lX05vZi6e2DuMEbvII2z7DIU9.BIN"
      },
      {
        "manifest": "crawler_manifest_v2.csv",
        "status": "downloaded",
        "label_raw": "OSCILLATION_CRASH",
        "source_type": "ArduPilot_Discuss",
        "thread_url": "https://discuss.ardupilot.org/t/quadcopter-crash-log-analysis-request/99897",
        "resolved_url": "https://discuss.ardupilot.org/uploads/short-url/a0lX05vZi6e2DuMEbvII2z7DIU9.BIN"
      }
    ],
    "expert_username": "",
    "expert_quote": "",
    "parse_message_count": 3000,
    "parse_message_types": 56
  },
  {
    "category": "verified_unlabeled",
    "file_name": "log_0070_radio_failsafe.bin",
    "source_path": "downloads/log_0070_radio_failsafe.bin",
    "source_relative_path": "downloads/log_0070_radio_failsafe.bin",
    "size_bytes": 749568,
    "sha256": "c35318e6ce5ed8bc79c3173b15fe88b912c4a6bb4c288b64c6fe18243df729bd",
    "duplicate_count": 1,
    "duplicate_sources": [
      "downloads/log_0070_radio_failsafe.bin"
    ],
    "raw_label": "RADIO_FAILSAFE",
    "mapped_label": "",
    "trainable": false,
    "source_type": "ArduPilot_Discuss",
    "source_url": "https://discuss.ardupilot.org/t/failsafe-sbus-not-working/65942",
    "resolved_download_url": "https://discuss.ardupilot.org/uploads/short-url/o6Lv7fXlIiQa0dskVenKbzoEN8u.bin",
    "provenance_status": "downloaded",
    "provenance_records": [
      {
        "manifest": "crawler_manifest.csv",
        "status": "downloaded",
        "label_raw": "RADIO_FAILSAFE",
        "source_type": "ArduPilot_Discuss",
        "thread_url": "https://discuss.ardupilot.org/t/failsafe-sbus-not-working/65942",
        "resolved_url": "https://discuss.ardupilot.org/uploads/short-url/o6Lv7fXlIiQa0dskVenKbzoEN8u.bin"
      },
      {
        "manifest": "crawler_manifest_v2.csv",
        "status": "downloaded",
        "label_raw": "RADIO_FAILSAFE",
        "source_type": "ArduPilot_Discuss",
        "thread_url": "https://discuss.ardupilot.org/t/failsafe-sbus-not-working/65942",
        "resolved_url": "https://discuss.ardupilot.org/uploads/short-url/o6Lv7fXlIiQa0dskVenKbzoEN8u.bin"
      }
    ],
    "expert_username": "xfacta",
    "expert_quote": "Yes that\u2019s the same as what I get. I have just bound a new receiver (during very low throttle) and Taranis is set to No Pulses. I\u2019m using ArduCopter V4.0.5 on this quad. Arducopter realises there\u2019s no pulses (PWM or SBUS) from the receiver and enters failsafe, same as if the throttle channel goes below the set PWM level. I have a throttle disable switch SF set to drop the throttle channel to 930 PWM or there-about. W",
    "parse_message_count": 3000,
    "parse_message_types": 47
  },
  {
    "category": "verified_unlabeled",
    "file_name": "log_0047_thrust_loss.bin",
    "source_path": "downloads/log_0047_thrust_loss.bin",
    "source_relative_path": "downloads/log_0047_thrust_loss.bin",
    "size_bytes": 534601,
    "sha256": "c55006bd101fd1d9f634eb61a56add2b9f644e29e767fbd0d5af5e0051827ad6",
    "duplicate_count": 1,
    "duplicate_sources": [
      "downloads/log_0047_thrust_loss.bin"
    ],
    "raw_label": "THRUST_LOSS",
    "mapped_label": "",
    "trainable": false,
    "source_type": "ArduPilot_Discuss",
    "source_url": "https://discuss.ardupilot.org/t/motors-maxing-out-when-flight/115319",
    "resolved_download_url": "https://discuss.ardupilot.org/uploads/short-url/kydAHmcjuJbVflTWP1qYXsmLNqL.BIN",
    "provenance_status": "downloaded",
    "provenance_records": [
      {
        "manifest": "crawler_manifest.csv",
        "status": "downloaded",
        "label_raw": "THRUST_LOSS",
        "source_type": "ArduPilot_Discuss",
        "thread_url": "https://discuss.ardupilot.org/t/motors-maxing-out-when-flight/115319",
        "resolved_url": "https://discuss.ardupilot.org/uploads/short-url/kydAHmcjuJbVflTWP1qYXsmLNqL.BIN"
      },
      {
        "manifest": "crawler_manifest_v2.csv",
        "status": "downloaded",
        "label_raw": "THRUST_LOSS",
        "source_type": "ArduPilot_Discuss",
        "thread_url": "https://discuss.ardupilot.org/t/motors-maxing-out-when-flight/115319",
        "resolved_url": "https://discuss.ardupilot.org/uploads/short-url/kydAHmcjuJbVflTWP1qYXsmLNqL.BIN"
      }
    ],
    "expert_username": "",
    "expert_quote": "",
    "parse_message_count": 3000,
    "parse_message_types": 44
  },
  {
    "category": "verified_unlabeled",
    "file_name": "log_0062_flyaway.bin",
    "source_path": "downloads/log_0062_flyaway.bin",
    "source_relative_path": "downloads/log_0062_flyaway.bin",
    "size_bytes": 1462272,
    "sha256": "c6d4e2f2539fc101acdfce3216d5cea54b9efa5e92303f7417d7f8aaa133865e",
    "duplicate_count": 1,
    "duplicate_sources": [
      "downloads/log_0062_flyaway.bin"
    ],
    "raw_label": "FLYAWAY",
    "mapped_label": "",
    "trainable": false,
    "source_type": "ArduPilot_Discuss",
    "source_url": "https://discuss.ardupilot.org/t/quad-flyaway-need-analysis/69210",
    "resolved_download_url": "https://www.dropbox.com/s/1hgy17ycvf4d7pv/00000029.BIN?dl=1",
    "provenance_status": "downloaded",
    "provenance_records": [
      {
        "manifest": "crawler_manifest.csv",
        "status": "downloaded",
        "label_raw": "FLYAWAY",
        "source_type": "ArduPilot_Discuss",
        "thread_url": "https://discuss.ardupilot.org/t/quad-flyaway-need-analysis/69210",
        "resolved_url": "https://www.dropbox.com/s/1hgy17ycvf4d7pv/00000029.BIN?dl=1"
      },
      {
        "manifest": "crawler_manifest_v2.csv",
        "status": "downloaded",
        "label_raw": "FLYAWAY",
        "source_type": "ArduPilot_Discuss",
        "thread_url": "https://discuss.ardupilot.org/t/quad-flyaway-need-analysis/69210",
        "resolved_url": "https://www.dropbox.com/s/1hgy17ycvf4d7pv/00000029.BIN?dl=1"
      }
    ],
    "expert_username": "",
    "expert_quote": "",
    "parse_message_count": 3000,
    "parse_message_types": 48
  },
  {
    "category": "verified_unlabeled",
    "file_name": "log_0057_oscillation_crash.bin",
    "source_path": "downloads/log_0057_oscillation_crash.bin",
    "source_relative_path": "downloads/log_0057_oscillation_crash.bin",
    "size_bytes": 3294211,
    "sha256": "ca2e821c6686411f14997b427dc7ebe286aa3fa41f6262d9ddd51a0f9f3cb65e",
    "duplicate_count": 1,
    "duplicate_sources": [
      "downloads/log_0057_oscillation_crash.bin"
    ],
    "raw_label": "OSCILLATION_CRASH",
    "mapped_label": "",
    "trainable": false,
    "source_type": "ArduPilot_Discuss",
    "source_url": "https://discuss.ardupilot.org/t/crash-when-switching-from-rtl-to-loiter/103732",
    "resolved_download_url": "https://www.dropbox.com/s/tg41eud2m9fwon5/00000022.BIN?dl=1",
    "provenance_status": "downloaded",
    "provenance_records": [
      {
        "manifest": "crawler_manifest.csv",
        "status": "downloaded",
        "label_raw": "OSCILLATION_CRASH",
        "source_type": "ArduPilot_Discuss",
        "thread_url": "https://discuss.ardupilot.org/t/crash-when-switching-from-rtl-to-loiter/103732",
        "resolved_url": "https://www.dropbox.com/s/tg41eud2m9fwon5/00000022.BIN?dl=1"
      },
      {
        "manifest": "crawler_manifest_v2.csv",
        "status": "downloaded",
        "label_raw": "OSCILLATION_CRASH",
        "source_type": "ArduPilot_Discuss",
        "thread_url": "https://discuss.ardupilot.org/t/crash-when-switching-from-rtl-to-loiter/103732",
        "resolved_url": "https://www.dropbox.com/s/tg41eud2m9fwon5/00000022.BIN?dl=1"
      }
    ],
    "expert_username": "",
    "expert_quote": "",
    "parse_message_count": 3000,
    "parse_message_types": 45
  },
  {
    "category": "verified_unlabeled",
    "file_name": "log_0069_radio_failsafe.bin",
    "source_path": "downloads/log_0069_radio_failsafe.bin",
    "source_relative_path": "downloads/log_0069_radio_failsafe.bin",
    "size_bytes": 630784,
    "sha256": "cdb6b1a5546b7f01c91fd16786e2cbda4d60a5f408ab1f3f7582628aa878498b",
    "duplicate_count": 1,
    "duplicate_sources": [
      "downloads/log_0069_radio_failsafe.bin"
    ],
    "raw_label": "RADIO_FAILSAFE",
    "mapped_label": "",
    "trainable": false,
    "source_type": "ArduPilot_Discuss",
    "source_url": "https://discuss.ardupilot.org/t/quadcopter-gives-radio-failsafe-and-climbs-to-15-meters-immidiately-after-arming/99762",
    "resolved_download_url": "https://discuss.ardupilot.org/uploads/short-url/ku59likLNhY6WZb65gQ3iz3O8Sc.bin",
    "provenance_status": "downloaded",
    "provenance_records": [
      {
        "manifest": "crawler_manifest.csv",
        "status": "downloaded",
        "label_raw": "RADIO_FAILSAFE",
        "source_type": "ArduPilot_Discuss",
        "thread_url": "https://discuss.ardupilot.org/t/quadcopter-gives-radio-failsafe-and-climbs-to-15-meters-immidiately-after-arming/99762",
        "resolved_url": "https://discuss.ardupilot.org/uploads/short-url/ku59likLNhY6WZb65gQ3iz3O8Sc.bin"
      },
      {
        "manifest": "crawler_manifest_v2.csv",
        "status": "downloaded",
        "label_raw": "RADIO_FAILSAFE",
        "source_type": "ArduPilot_Discuss",
        "thread_url": "https://discuss.ardupilot.org/t/quadcopter-gives-radio-failsafe-and-climbs-to-15-meters-immidiately-after-arming/99762",
        "resolved_url": "https://discuss.ardupilot.org/uploads/short-url/ku59likLNhY6WZb65gQ3iz3O8Sc.bin"
      }
    ],
    "expert_username": "",
    "expert_quote": "",
    "parse_message_count": 3000,
    "parse_message_types": 49
  },
  {
    "category": "verified_labeled",
    "file_name": "log_0038_mechanical_failure.bin",
    "source_path": "downloads/log_0038_mechanical_failure.bin",
    "source_relative_path": "downloads/log_0038_mechanical_failure.bin",
    "size_bytes": 364323,
    "sha256": "cf337b4dde9a1f203b7ceb588c591241e2acac577124e89d88f2b8783efef043",
    "duplicate_count": 1,
    "duplicate_sources": [
      "downloads/log_0038_mechanical_failure.bin"
    ],
    "raw_label": "MECHANICAL_FAILURE",
    "mapped_label": "mechanical_failure",
    "trainable": true,
    "source_type": "ArduPilot_Discuss",
    "source_url": "https://discuss.ardupilot.org/t/esc-failure-or-signal-lost-thank-s-for-help/18093",
    "resolved_download_url": "https://discuss.ardupilot.org/uploads/default/original/2X/d/d69429de5eed1d724bd8643db7173e07453ee55c.BIN",
    "provenance_status": "downloaded",
    "provenance_records": [
      {
        "manifest": "crawler_manifest.csv",
        "status": "downloaded",
        "label_raw": "MECHANICAL_FAILURE",
        "source_type": "ArduPilot_Discuss",
        "thread_url": "https://discuss.ardupilot.org/t/esc-failure-or-signal-lost-thank-s-for-help/18093",
        "resolved_url": "https://discuss.ardupilot.org/uploads/default/original/2X/d/d69429de5eed1d724bd8643db7173e07453ee55c.BIN"
      },
      {
        "manifest": "crawler_manifest_v2.csv",
        "status": "downloaded",
        "label_raw": "MECHANICAL_FAILURE",
        "source_type": "ArduPilot_Discuss",
        "thread_url": "https://discuss.ardupilot.org/t/esc-failure-or-signal-lost-thank-s-for-help/18093",
        "resolved_url": "https://discuss.ardupilot.org/uploads/default/original/2X/d/d69429de5eed1d724bd8643db7173e07453ee55c.BIN"
      }
    ],
    "expert_username": "",
    "expert_quote": "",
    "parse_message_count": 3000,
    "parse_message_types": 39
  },
  {
    "category": "verified_labeled",
    "file_name": "log_0037_mechanical_failure.bin",
    "source_path": "downloads/log_0037_mechanical_failure.bin",
    "source_relative_path": "downloads/log_0037_mechanical_failure.bin",
    "size_bytes": 6513226,
    "sha256": "d3ecd87205ba32a8effd9f2e78443bee25ffd0baa8be333c78bd404f641cf81f",
    "duplicate_count": 1,
    "duplicate_sources": [
      "downloads/log_0037_mechanical_failure.bin"
    ],
    "raw_label": "MECHANICAL_FAILURE",
    "mapped_label": "mechanical_failure",
    "trainable": true,
    "source_type": "ArduPilot_Discuss",
    "source_url": "https://discuss.ardupilot.org/t/hexacopter-redundancy/72447",
    "resolved_download_url": "https://www.dropbox.com/s/vf00f1dkj495oar/log_27_2021-5-1-15-46-46.bin?dl=1",
    "provenance_status": "downloaded",
    "provenance_records": [
      {
        "manifest": "crawler_manifest.csv",
        "status": "downloaded",
        "label_raw": "MECHANICAL_FAILURE",
        "source_type": "ArduPilot_Discuss",
        "thread_url": "https://discuss.ardupilot.org/t/hexacopter-redundancy/72447",
        "resolved_url": "https://www.dropbox.com/s/vf00f1dkj495oar/log_27_2021-5-1-15-46-46.bin?dl=1"
      },
      {
        "manifest": "crawler_manifest_v2.csv",
        "status": "downloaded",
        "label_raw": "MECHANICAL_FAILURE",
        "source_type": "ArduPilot_Discuss",
        "thread_url": "https://discuss.ardupilot.org/t/hexacopter-redundancy/72447",
        "resolved_url": "https://www.dropbox.com/s/vf00f1dkj495oar/log_27_2021-5-1-15-46-46.bin?dl=1"
      }
    ],
    "expert_username": "",
    "expert_quote": "",
    "parse_message_count": 3000,
    "parse_message_types": 54
  },
  {
    "category": "verified_unlabeled",
    "file_name": "log_0046_thrust_loss.bin",
    "source_path": "downloads/log_0046_thrust_loss.bin",
    "source_relative_path": "downloads/log_0046_thrust_loss.bin",
    "size_bytes": 3188569,
    "sha256": "d5095b90be9440b7ef0528d2ddbdf945f3f3f774d3517335464974cdf37fcba8",
    "duplicate_count": 1,
    "duplicate_sources": [
      "downloads/log_0046_thrust_loss.bin"
    ],
    "raw_label": "THRUST_LOSS",
    "mapped_label": "",
    "trainable": false,
    "source_type": "ArduPilot_Discuss",
    "source_url": "https://discuss.ardupilot.org/t/im-new-unable-to-take-off-on-stabilize-or-lotier/9348",
    "resolved_download_url": "https://www.dropbox.com/s/z57c5ddb69oiwoj/4%205-29-2016%207-41-20%20PM.bin?dl=1",
    "provenance_status": "downloaded",
    "provenance_records": [
      {
        "manifest": "crawler_manifest.csv",
        "status": "downloaded",
        "label_raw": "THRUST_LOSS",
        "source_type": "ArduPilot_Discuss",
        "thread_url": "https://discuss.ardupilot.org/t/im-new-unable-to-take-off-on-stabilize-or-lotier/9348",
        "resolved_url": "https://www.dropbox.com/s/z57c5ddb69oiwoj/4%205-29-2016%207-41-20%20PM.bin?dl=1"
      },
      {
        "manifest": "crawler_manifest_v2.csv",
        "status": "downloaded",
        "label_raw": "THRUST_LOSS",
        "source_type": "ArduPilot_Discuss",
        "thread_url": "https://discuss.ardupilot.org/t/im-new-unable-to-take-off-on-stabilize-or-lotier/9348",
        "resolved_url": "https://www.dropbox.com/s/z57c5ddb69oiwoj/4%205-29-2016%207-41-20%20PM.bin?dl=1"
      }
    ],
    "expert_username": "",
    "expert_quote": "",
    "parse_message_count": 3000,
    "parse_message_types": 34
  },
  {
    "category": "verified_labeled",
    "file_name": "log_0036_mechanical_failure.bin",
    "source_path": "downloads/log_0036_mechanical_failure.bin",
    "source_relative_path": "downloads/log_0036_mechanical_failure.bin",
    "size_bytes": 1751678,
    "sha256": "d9464b12aaed79a5ea7f7c626bd96d83037db37018deff5c2399d078a9d155fe",
    "duplicate_count": 1,
    "duplicate_sources": [
      "downloads/log_0036_mechanical_failure.bin"
    ],
    "raw_label": "MECHANICAL_FAILURE",
    "mapped_label": "mechanical_failure",
    "trainable": true,
    "source_type": "ArduPilot_Discuss",
    "source_url": "https://discuss.ardupilot.org/t/copter-3-4-4-rc1-available-for-beta-testing/13645",
    "resolved_download_url": "https://discuss.ardupilot.org/uploads/default/original/2X/4/4410a788d8c043cf704a45ee850a6a0071d9909a.BIN",
    "provenance_status": "downloaded",
    "provenance_records": [
      {
        "manifest": "crawler_manifest.csv",
        "status": "downloaded",
        "label_raw": "MECHANICAL_FAILURE",
        "source_type": "ArduPilot_Discuss",
        "thread_url": "https://discuss.ardupilot.org/t/copter-3-4-4-rc1-available-for-beta-testing/13645",
        "resolved_url": "https://discuss.ardupilot.org/uploads/default/original/2X/4/4410a788d8c043cf704a45ee850a6a0071d9909a.BIN"
      },
      {
        "manifest": "crawler_manifest_v2.csv",
        "status": "downloaded",
        "label_raw": "MECHANICAL_FAILURE",
        "source_type": "ArduPilot_Discuss",
        "thread_url": "https://discuss.ardupilot.org/t/copter-3-4-4-rc1-available-for-beta-testing/13645",
        "resolved_url": "https://discuss.ardupilot.org/uploads/default/original/2X/4/4410a788d8c043cf704a45ee850a6a0071d9909a.BIN"
      }
    ],
    "expert_username": "",
    "expert_quote": "",
    "parse_message_count": 3000,
    "parse_message_types": 39
  },
  {
    "category": "verified_unlabeled",
    "file_name": "log_0068_uncontrolled_descent.bin",
    "source_path": "downloads/log_0068_uncontrolled_descent.bin",
    "source_relative_path": "downloads/log_0068_uncontrolled_descent.bin",
    "size_bytes": 380928,
    "sha256": "e37a094bd36b9572806acfd0701214927028bffce22d8ab38877549ba95e87a5",
    "duplicate_count": 1,
    "duplicate_sources": [
      "downloads/log_0068_uncontrolled_descent.bin"
    ],
    "raw_label": "UNCONTROLLED_DESCENT",
    "mapped_label": "",
    "trainable": false,
    "source_type": "ArduPilot_Discuss",
    "source_url": "https://discuss.ardupilot.org/t/copter-unexpected-rapid-climb-after-arming-eventually-crashed/119799",
    "resolved_download_url": "https://discuss.ardupilot.org/uploads/short-url/1UI00F4UErnpVfoG5geJsTPRa6M.BIN",
    "provenance_status": "downloaded",
    "provenance_records": [
      {
        "manifest": "crawler_manifest.csv",
        "status": "downloaded",
        "label_raw": "UNCONTROLLED_DESCENT",
        "source_type": "ArduPilot_Discuss",
        "thread_url": "https://discuss.ardupilot.org/t/copter-unexpected-rapid-climb-after-arming-eventually-crashed/119799",
        "resolved_url": "https://discuss.ardupilot.org/uploads/short-url/1UI00F4UErnpVfoG5geJsTPRa6M.BIN"
      },
      {
        "manifest": "crawler_manifest_v2.csv",
        "status": "downloaded",
        "label_raw": "UNCONTROLLED_DESCENT",
        "source_type": "ArduPilot_Discuss",
        "thread_url": "https://discuss.ardupilot.org/t/copter-unexpected-rapid-climb-after-arming-eventually-crashed/119799",
        "resolved_url": "https://discuss.ardupilot.org/uploads/short-url/1UI00F4UErnpVfoG5geJsTPRa6M.BIN"
      }
    ],
    "expert_username": "",
    "expert_quote": "",
    "parse_message_count": 3000,
    "parse_message_types": 51
  },
  {
    "category": "verified_labeled",
    "file_name": "log_0042_mechanical_failure.bin",
    "source_path": "downloads/log_0042_mechanical_failure.bin",
    "source_relative_path": "downloads/log_0042_mechanical_failure.bin",
    "size_bytes": 49229824,
    "sha256": "e3c66d3ea3e373cb384166ef0f70ed27a2aad71ded3404d56f0681ef2f9cd962",
    "duplicate_count": 1,
    "duplicate_sources": [
      "downloads/log_0042_mechanical_failure.bin"
    ],
    "raw_label": "MECHANICAL_FAILURE",
    "mapped_label": "mechanical_failure",
    "trainable": true,
    "source_type": "ArduPilot_Discuss",
    "source_url": "https://discuss.ardupilot.org/t/fixed-wing-dead-reckoning-test-of-the-zealot-h743-aero-applications-edition/101680",
    "resolved_download_url": "https://www.dropbox.com/s/jj3j5zdgpeqh5v0/log_56_UnknownDate.bin?dl=1",
    "provenance_status": "downloaded",
    "provenance_records": [
      {
        "manifest": "crawler_manifest.csv",
        "status": "downloaded",
        "label_raw": "MECHANICAL_FAILURE",
        "source_type": "ArduPilot_Discuss",
        "thread_url": "https://discuss.ardupilot.org/t/fixed-wing-dead-reckoning-test-of-the-zealot-h743-aero-applications-edition/101680",
        "resolved_url": "https://www.dropbox.com/s/jj3j5zdgpeqh5v0/log_56_UnknownDate.bin?dl=1"
      },
      {
        "manifest": "crawler_manifest_v2.csv",
        "status": "downloaded",
        "label_raw": "MECHANICAL_FAILURE",
        "source_type": "ArduPilot_Discuss",
        "thread_url": "https://discuss.ardupilot.org/t/fixed-wing-dead-reckoning-test-of-the-zealot-h743-aero-applications-edition/101680",
        "resolved_url": "https://www.dropbox.com/s/jj3j5zdgpeqh5v0/log_56_UnknownDate.bin?dl=1"
      }
    ],
    "expert_username": "timtuxworth",
    "expert_quote": "I plan to test dead reckoning using intertial navigation on the Qio-Tek Zealot H743 \u201cAero Applications Edition\u201d which has an IIM-42652, ICM-42688P and an ADIS\u201316470 IMU. Also: Barometers: DPS3018 *2 Compass: QMC5883L I\u2019ll also install an ASP-5033 Airspeed sensor (using DroneCAN of course). I know I can \u201cdisable\u201d GPS in software, but call me cynical, I want to be 100% sure that while flying with no GPS, there is no ch",
    "parse_message_count": 3000,
    "parse_message_types": 57
  },
  {
    "category": "verified_unlabeled",
    "file_name": "log_0048_oscillation_crash.bin",
    "source_path": "downloads/log_0048_oscillation_crash.bin",
    "source_relative_path": "downloads/log_0048_oscillation_crash.bin",
    "size_bytes": 32065861,
    "sha256": "f7d7a771d1b12dda9e1b19c21d6e6941822d5c319beb930b89920f6bde54181e",
    "duplicate_count": 1,
    "duplicate_sources": [
      "downloads/log_0048_oscillation_crash.bin"
    ],
    "raw_label": "OSCILLATION_CRASH",
    "mapped_label": "",
    "trainable": false,
    "source_type": "ArduPilot_Discuss",
    "source_url": "https://discuss.ardupilot.org/t/oscillation-in-roll-and-pitch-resulting-in-crash/93512",
    "resolved_download_url": "https://www.dropbox.com/s/n9z1j2w90xncrf7/00000082.BIN?dl=1",
    "provenance_status": "downloaded",
    "provenance_records": [
      {
        "manifest": "crawler_manifest.csv",
        "status": "downloaded",
        "label_raw": "OSCILLATION_CRASH",
        "source_type": "ArduPilot_Discuss",
        "thread_url": "https://discuss.ardupilot.org/t/oscillation-in-roll-and-pitch-resulting-in-crash/93512",
        "resolved_url": "https://www.dropbox.com/s/n9z1j2w90xncrf7/00000082.BIN?dl=1"
      },
      {
        "manifest": "crawler_manifest_v2.csv",
        "status": "downloaded",
        "label_raw": "OSCILLATION_CRASH",
        "source_type": "ArduPilot_Discuss",
        "thread_url": "https://discuss.ardupilot.org/t/oscillation-in-roll-and-pitch-resulting-in-crash/93512",
        "resolved_url": "https://www.dropbox.com/s/n9z1j2w90xncrf7/00000082.BIN?dl=1"
      }
    ],
    "expert_username": "",
    "expert_quote": "",
    "parse_message_count": 3000,
    "parse_message_types": 55
  },
  {
    "category": "verified_unlabeled",
    "file_name": "log_0050_oscillation_crash.bin",
    "source_path": "downloads/log_0050_oscillation_crash.bin",
    "source_relative_path": "downloads/log_0050_oscillation_crash.bin",
    "size_bytes": 868352,
    "sha256": "fa2f67b19dcbb58b7b7ac1797f44d59957fafa1f932aa06218555e3f465df0ce",
    "duplicate_count": 1,
    "duplicate_sources": [
      "downloads/log_0050_oscillation_crash.bin"
    ],
    "raw_label": "OSCILLATION_CRASH",
    "mapped_label": "",
    "trainable": false,
    "source_type": "ArduPilot_Discuss",
    "source_url": "https://discuss.ardupilot.org/t/quadcopter-crash-log-analysis-request/99897",
    "resolved_download_url": "https://discuss.ardupilot.org/uploads/short-url/uDShwPTvBHO5pUYpWxTeMEMCVp5.BIN",
    "provenance_status": "downloaded",
    "provenance_records": [
      {
        "manifest": "crawler_manifest.csv",
        "status": "downloaded",
        "label_raw": "OSCILLATION_CRASH",
        "source_type": "ArduPilot_Discuss",
        "thread_url": "https://discuss.ardupilot.org/t/quadcopter-crash-log-analysis-request/99897",
        "resolved_url": "https://discuss.ardupilot.org/uploads/short-url/uDShwPTvBHO5pUYpWxTeMEMCVp5.BIN"
      },
      {
        "manifest": "crawler_manifest_v2.csv",
        "status": "downloaded",
        "label_raw": "OSCILLATION_CRASH",
        "source_type": "ArduPilot_Discuss",
        "thread_url": "https://discuss.ardupilot.org/t/quadcopter-crash-log-analysis-request/99897",
        "resolved_url": "https://discuss.ardupilot.org/uploads/short-url/uDShwPTvBHO5pUYpWxTeMEMCVp5.BIN"
      }
    ],
    "expert_username": "",
    "expert_quote": "",
    "parse_message_count": 3000,
    "parse_message_types": 53
  },
  {
    "category": "verified_unlabeled",
    "file_name": "log_0053_oscillation_crash.bin",
    "source_path": "downloads/log_0053_oscillation_crash.bin",
    "source_relative_path": "downloads/log_0053_oscillation_crash.bin",
    "size_bytes": 22588536,
    "sha256": "fb32889d51090b69f75118e7a543457993575a0a7d38e299e0e647cc3ec77040",
    "duplicate_count": 1,
    "duplicate_sources": [
      "downloads/log_0053_oscillation_crash.bin"
    ],
    "raw_label": "OSCILLATION_CRASH",
    "mapped_label": "",
    "trainable": false,
    "source_type": "ArduPilot_Discuss",
    "source_url": "https://discuss.ardupilot.org/t/tuning-issues-with-plane-successful-auto-t-o-and-land-maiden-now-not-so-much/100608",
    "resolved_download_url": "https://www.dropbox.com/s/ecm1bkp071v2r1b/2023-05-06%20Sortie%202.bin?dl=1",
    "provenance_status": "downloaded",
    "provenance_records": [
      {
        "manifest": "crawler_manifest.csv",
        "status": "downloaded",
        "label_raw": "OSCILLATION_CRASH",
        "source_type": "ArduPilot_Discuss",
        "thread_url": "https://discuss.ardupilot.org/t/tuning-issues-with-plane-successful-auto-t-o-and-land-maiden-now-not-so-much/100608",
        "resolved_url": "https://www.dropbox.com/s/ecm1bkp071v2r1b/2023-05-06%20Sortie%202.bin?dl=1"
      },
      {
        "manifest": "crawler_manifest_v2.csv",
        "status": "downloaded",
        "label_raw": "OSCILLATION_CRASH",
        "source_type": "ArduPilot_Discuss",
        "thread_url": "https://discuss.ardupilot.org/t/tuning-issues-with-plane-successful-auto-t-o-and-land-maiden-now-not-so-much/100608",
        "resolved_url": "https://www.dropbox.com/s/ecm1bkp071v2r1b/2023-05-06%20Sortie%202.bin?dl=1"
      }
    ],
    "expert_username": "",
    "expert_quote": "",
    "parse_message_count": 3000,
    "parse_message_types": 52
  },
  {
    "category": "excluded_archive",
    "file_name": "log_0014_compass_interference.zip",
    "source_path": "downloads/log_0014_compass_interference.zip",
    "source_relative_path": "downloads/log_0014_compass_interference.zip",
    "size_bytes": 1255,
    "sha256": "529e1dbbd27130eeaaf60c12f9b92cbca4b29295e189af64510fd26a24859b4c",
    "duplicate_count": 1,
    "duplicate_sources": [
      "downloads/log_0014_compass_interference.zip"
    ],
    "raw_label": "COMPASS_INTERFERENCE",
    "mapped_label": "",
    "trainable": false,
    "source_type": "ArduPilot_Discuss",
    "source_url": "https://discuss.ardupilot.org/t/crash-spinning-quad-on-pixracer-r15-arducopter-3-6-6/38666",
    "resolved_download_url": "https://discuss.ardupilot.org/uploads/default/original/3X/2/1/2171cb7df0f5e05ccf0ab8d94e15780afacc260e.zip",
    "provenance_status": "downloaded",
    "provenance_records": [
      {
        "manifest": "crawler_manifest.csv",
        "status": "downloaded",
        "label_raw": "COMPASS_INTERFERENCE",
        "source_type": "ArduPilot_Discuss",
        "thread_url": "https://discuss.ardupilot.org/t/crash-spinning-quad-on-pixracer-r15-arducopter-3-6-6/38666",
        "resolved_url": "https://discuss.ardupilot.org/uploads/default/original/3X/2/1/2171cb7df0f5e05ccf0ab8d94e15780afacc260e.zip"
      },
      {
        "manifest": "crawler_manifest_v2.csv",
        "status": "downloaded",
        "label_raw": "COMPASS_INTERFERENCE",
        "source_type": "ArduPilot_Discuss",
        "thread_url": "https://discuss.ardupilot.org/t/crash-spinning-quad-on-pixracer-r15-arducopter-3-6-6/38666",
        "resolved_url": "https://discuss.ardupilot.org/uploads/default/original/3X/2/1/2171cb7df0f5e05ccf0ab8d94e15780afacc260e.zip"
      }
    ],
    "expert_username": "",
    "expert_quote": "",
    "parse_message_count": 0,
    "parse_message_types": 0
  },
  {
    "category": "excluded_archive",
    "file_name": "log_0031_battery_failsafe.zip",
    "source_path": "downloads/log_0031_battery_failsafe.zip",
    "source_relative_path": "downloads/log_0031_battery_failsafe.zip",
    "size_bytes": 152187,
    "sha256": "5ae764880a5d4f14ad5adb2494d4f17520bf077621af48ef42b5c56ec69d5f50",
    "duplicate_count": 1,
    "duplicate_sources": [
      "downloads/log_0031_battery_failsafe.zip"
    ],
    "raw_label": "BATTERY_FAILSAFE",
    "mapped_label": "",
    "trainable": false,
    "source_type": "ArduPilot_Discuss",
    "source_url": "https://discuss.ardupilot.org/t/pixhawk-motor-balance-warn/33051",
    "resolved_download_url": "https://discuss.ardupilot.org/uploads/default/original/3X/5/3/53ab529832100fd7cd5fc23fe86ea39602ce70ff.zip",
    "provenance_status": "downloaded",
    "provenance_records": [
      {
        "manifest": "crawler_manifest.csv",
        "status": "downloaded",
        "label_raw": "BATTERY_FAILSAFE",
        "source_type": "ArduPilot_Discuss",
        "thread_url": "https://discuss.ardupilot.org/t/pixhawk-motor-balance-warn/33051",
        "resolved_url": "https://discuss.ardupilot.org/uploads/default/original/3X/5/3/53ab529832100fd7cd5fc23fe86ea39602ce70ff.zip"
      },
      {
        "manifest": "crawler_manifest_v2.csv",
        "status": "downloaded",
        "label_raw": "BATTERY_FAILSAFE",
        "source_type": "ArduPilot_Discuss",
        "thread_url": "https://discuss.ardupilot.org/t/pixhawk-motor-balance-warn/33051",
        "resolved_url": "https://discuss.ardupilot.org/uploads/default/original/3X/5/3/53ab529832100fd7cd5fc23fe86ea39602ce70ff.zip"
      }
    ],
    "expert_username": "",
    "expert_quote": "",
    "parse_message_count": 0,
    "parse_message_types": 0
  },
  {
    "category": "excluded_archive",
    "file_name": "log_0024_sudden_yaw.zip",
    "source_path": "downloads/log_0024_sudden_yaw.zip",
    "source_relative_path": "downloads/log_0024_sudden_yaw.zip",
    "size_bytes": 4495851,
    "sha256": "b40fb82a488257778b3e1ca7cc8a25cdfe11d897c90667ea6e88a5252dc8fbed",
    "duplicate_count": 1,
    "duplicate_sources": [
      "downloads/log_0024_sudden_yaw.zip"
    ],
    "raw_label": "SUDDEN_YAW",
    "mapped_label": "",
    "trainable": false,
    "source_type": "ArduPilot_Discuss",
    "source_url": "https://discuss.ardupilot.org/t/pixhawk-flyaway-in-stabilized-mode-with-complete-loss-of-control/13560",
    "resolved_download_url": "https://discuss.ardupilot.org/uploads/default/original/2X/8/8d08c5e9574fec07fd69d75b99406483e876775f.zip",
    "provenance_status": "downloaded",
    "provenance_records": [
      {
        "manifest": "crawler_manifest.csv",
        "status": "downloaded",
        "label_raw": "SUDDEN_YAW",
        "source_type": "ArduPilot_Discuss",
        "thread_url": "https://discuss.ardupilot.org/t/pixhawk-flyaway-in-stabilized-mode-with-complete-loss-of-control/13560",
        "resolved_url": "https://discuss.ardupilot.org/uploads/default/original/2X/8/8d08c5e9574fec07fd69d75b99406483e876775f.zip"
      },
      {
        "manifest": "crawler_manifest_v2.csv",
        "status": "downloaded",
        "label_raw": "SUDDEN_YAW",
        "source_type": "ArduPilot_Discuss",
        "thread_url": "https://discuss.ardupilot.org/t/pixhawk-flyaway-in-stabilized-mode-with-complete-loss-of-control/13560",
        "resolved_url": "https://discuss.ardupilot.org/uploads/default/original/2X/8/8d08c5e9574fec07fd69d75b99406483e876775f.zip"
      }
    ],
    "expert_username": "",
    "expert_quote": "",
    "parse_message_count": 0,
    "parse_message_types": 0
  },
  {
    "category": "excluded_archive",
    "file_name": "log_0009_compass_interference.zip",
    "source_path": "downloads/log_0009_compass_interference.zip",
    "source_relative_path": "downloads/log_0009_compass_interference.zip",
    "size_bytes": 1019903,
    "sha256": "c55dea6f970ba670e48864a1596a182297ba7e4809e9f2693a49a7694d873a7c",
    "duplicate_count": 1,
    "duplicate_sources": [
      "downloads/log_0009_compass_interference.zip"
    ],
    "raw_label": "COMPASS_INTERFERENCE",
    "mapped_label": "",
    "trainable": false,
    "source_type": "ArduPilot_Discuss",
    "source_url": "https://discuss.ardupilot.org/t/hexacopter-drifting-away-crash-log-video/26675",
    "resolved_download_url": "https://discuss.ardupilot.org/uploads/default/original/2X/a/a24e9cfb9ae25e08979a327589b805e2bcbc122c.zip",
    "provenance_status": "downloaded",
    "provenance_records": [
      {
        "manifest": "crawler_manifest.csv",
        "status": "downloaded",
        "label_raw": "COMPASS_INTERFERENCE",
        "source_type": "ArduPilot_Discuss",
        "thread_url": "https://discuss.ardupilot.org/t/hexacopter-drifting-away-crash-log-video/26675",
        "resolved_url": "https://discuss.ardupilot.org/uploads/default/original/2X/a/a24e9cfb9ae25e08979a327589b805e2bcbc122c.zip"
      },
      {
        "manifest": "crawler_manifest_v2.csv",
        "status": "downloaded",
        "label_raw": "COMPASS_INTERFERENCE",
        "source_type": "ArduPilot_Discuss",
        "thread_url": "https://discuss.ardupilot.org/t/hexacopter-drifting-away-crash-log-video/26675",
        "resolved_url": "https://discuss.ardupilot.org/uploads/default/original/2X/a/a24e9cfb9ae25e08979a327589b805e2bcbc122c.zip"
      }
    ],
    "expert_username": "",
    "expert_quote": "",
    "parse_message_count": 0,
    "parse_message_types": 0
  },
  {
    "category": "excluded_archive",
    "file_name": "log_0035_hardware_failure.zip",
    "source_path": "downloads/log_0035_hardware_failure.zip",
    "source_relative_path": "downloads/log_0035_hardware_failure.zip",
    "size_bytes": 123438,
    "sha256": "cbe1fbcaed7e8e7837cf79aaed08be21822433569edfc8334064d5490dd8ffb4",
    "duplicate_count": 1,
    "duplicate_sources": [
      "downloads/log_0035_hardware_failure.zip"
    ],
    "raw_label": "HARDWARE_FAILURE",
    "mapped_label": "",
    "trainable": false,
    "source_type": "ArduPilot_Discuss",
    "source_url": "https://discuss.ardupilot.org/t/prearm-crashdump-data-detected-arduplane-4-6-2/140189",
    "resolved_download_url": "https://discuss.ardupilot.org/uploads/short-url/fi92jRjELjQExhvFdhEuxwCO8Zw.zip",
    "provenance_status": "downloaded",
    "provenance_records": [
      {
        "manifest": "crawler_manifest.csv",
        "status": "downloaded",
        "label_raw": "HARDWARE_FAILURE",
        "source_type": "ArduPilot_Discuss",
        "thread_url": "https://discuss.ardupilot.org/t/prearm-crashdump-data-detected-arduplane-4-6-2/140189",
        "resolved_url": "https://discuss.ardupilot.org/uploads/short-url/fi92jRjELjQExhvFdhEuxwCO8Zw.zip"
      },
      {
        "manifest": "crawler_manifest_v2.csv",
        "status": "downloaded",
        "label_raw": "HARDWARE_FAILURE",
        "source_type": "ArduPilot_Discuss",
        "thread_url": "https://discuss.ardupilot.org/t/prearm-crashdump-data-detected-arduplane-4-6-2/140189",
        "resolved_url": "https://discuss.ardupilot.org/uploads/short-url/fi92jRjELjQExhvFdhEuxwCO8Zw.zip"
      }
    ],
    "expert_username": "",
    "expert_quote": "",
    "parse_message_count": 0,
    "parse_message_types": 0
  },
  {
    "category": "excluded_archive",
    "file_name": "log_0013_compass_interference.zip",
    "source_path": "downloads/log_0013_compass_interference.zip",
    "source_relative_path": "downloads/log_0013_compass_interference.zip",
    "size_bytes": 1895204,
    "sha256": "e21ed44cd5684cc210eeb72c56815b551fe5488ea490dbd483f376803e4b78a5",
    "duplicate_count": 1,
    "duplicate_sources": [
      "downloads/log_0013_compass_interference.zip"
    ],
    "raw_label": "COMPASS_INTERFERENCE",
    "mapped_label": "",
    "trainable": false,
    "source_type": "ArduPilot_Discuss",
    "source_url": "https://discuss.ardupilot.org/t/copter-3-4-rc5-possible-imu-or-compass-issues/11636",
    "resolved_download_url": "https://discuss.ardupilot.org/uploads/default/original/2X/f/f763ac9bcc8045da915143af8dc48d7db71ec2f5.zip",
    "provenance_status": "downloaded",
    "provenance_records": [
      {
        "manifest": "crawler_manifest.csv",
        "status": "downloaded",
        "label_raw": "COMPASS_INTERFERENCE",
        "source_type": "ArduPilot_Discuss",
        "thread_url": "https://discuss.ardupilot.org/t/copter-3-4-rc5-possible-imu-or-compass-issues/11636",
        "resolved_url": "https://discuss.ardupilot.org/uploads/default/original/2X/f/f763ac9bcc8045da915143af8dc48d7db71ec2f5.zip"
      },
      {
        "manifest": "crawler_manifest_v2.csv",
        "status": "downloaded",
        "label_raw": "COMPASS_INTERFERENCE",
        "source_type": "ArduPilot_Discuss",
        "thread_url": "https://discuss.ardupilot.org/t/copter-3-4-rc5-possible-imu-or-compass-issues/11636",
        "resolved_url": "https://discuss.ardupilot.org/uploads/default/original/2X/f/f763ac9bcc8045da915143af8dc48d7db71ec2f5.zip"
      }
    ],
    "expert_username": "",
    "expert_quote": "",
    "parse_message_count": 0,
    "parse_message_types": 0
  },
  {
    "category": "excluded_archive",
    "file_name": "log_0019_sudden_yaw.zip",
    "source_path": "downloads/log_0019_sudden_yaw.zip",
    "source_relative_path": "downloads/log_0019_sudden_yaw.zip",
    "size_bytes": 875178,
    "sha256": "f3a6f273d60a326d8bbdff65c4bf582135ea787391d2330bbcd695b3526f0f0e",
    "duplicate_count": 1,
    "duplicate_sources": [
      "downloads/log_0019_sudden_yaw.zip"
    ],
    "raw_label": "SUDDEN_YAW",
    "mapped_label": "",
    "trainable": false,
    "source_type": "ArduPilot_Discuss",
    "source_url": "https://discuss.ardupilot.org/t/tricopter-vtol-servos-cooking-vtol-roll-control-inverted/95543",
    "resolved_download_url": "https://discuss.ardupilot.org/uploads/short-url/nwJ7pCEheuQ1c6z6gpG34BpDhqx.zip",
    "provenance_status": "downloaded",
    "provenance_records": [
      {
        "manifest": "crawler_manifest.csv",
        "status": "downloaded",
        "label_raw": "SUDDEN_YAW",
        "source_type": "ArduPilot_Discuss",
        "thread_url": "https://discuss.ardupilot.org/t/tricopter-vtol-servos-cooking-vtol-roll-control-inverted/95543",
        "resolved_url": "https://discuss.ardupilot.org/uploads/short-url/nwJ7pCEheuQ1c6z6gpG34BpDhqx.zip"
      },
      {
        "manifest": "crawler_manifest_v2.csv",
        "status": "downloaded",
        "label_raw": "SUDDEN_YAW",
        "source_type": "ArduPilot_Discuss",
        "thread_url": "https://discuss.ardupilot.org/t/tricopter-vtol-servos-cooking-vtol-roll-control-inverted/95543",
        "resolved_url": "https://discuss.ardupilot.org/uploads/short-url/nwJ7pCEheuQ1c6z6gpG34BpDhqx.zip"
      }
    ],
    "expert_username": "",
    "expert_quote": "",
    "parse_message_count": 0,
    "parse_message_types": 0
  },
  {
    "category": "excluded_archive",
    "file_name": "log_0051_oscillation_crash.zip",
    "source_path": "downloads/log_0051_oscillation_crash.zip",
    "source_relative_path": "downloads/log_0051_oscillation_crash.zip",
    "size_bytes": 984753,
    "sha256": "fda6b2ec3b5fab004bd93bf70075fd4481ad8b748a757a430f62e3a6fd9fbcf6",
    "duplicate_count": 1,
    "duplicate_sources": [
      "downloads/log_0051_oscillation_crash.zip"
    ],
    "raw_label": "OSCILLATION_CRASH",
    "mapped_label": "",
    "trainable": false,
    "source_type": "ArduPilot_Discuss",
    "source_url": "https://discuss.ardupilot.org/t/quadcopter-crash-log-analysis-request/99897",
    "resolved_download_url": "https://discuss.ardupilot.org/uploads/short-url/yO5FfjO9MrQMNFiuPvyN1kZbKwU.zip",
    "provenance_status": "downloaded",
    "provenance_records": [
      {
        "manifest": "crawler_manifest.csv",
        "status": "downloaded",
        "label_raw": "OSCILLATION_CRASH",
        "source_type": "ArduPilot_Discuss",
        "thread_url": "https://discuss.ardupilot.org/t/quadcopter-crash-log-analysis-request/99897",
        "resolved_url": "https://discuss.ardupilot.org/uploads/short-url/yO5FfjO9MrQMNFiuPvyN1kZbKwU.zip"
      },
      {
        "manifest": "crawler_manifest_v2.csv",
        "status": "downloaded",
        "label_raw": "OSCILLATION_CRASH",
        "source_type": "ArduPilot_Discuss",
        "thread_url": "https://discuss.ardupilot.org/t/quadcopter-crash-log-analysis-request/99897",
        "resolved_url": "https://discuss.ardupilot.org/uploads/short-url/yO5FfjO9MrQMNFiuPvyN1kZbKwU.zip"
      }
    ],
    "expert_username": "",
    "expert_quote": "",
    "parse_message_count": 0,
    "parse_message_types": 0
  }
]
